{
"meta":{"test_sets":[],"test_metrics":[],"learn_metrics":[{"best_value":"Min","name":"RMSE"}],"launch_mode":"Train","parameters":"","iteration_count":1000,"learn_sets":["learn"],"name":"experiment"},
"iterations":[
{"learn":[3.024793921],"iteration":0,"passed_time":0.00119778189,"remaining_time":1.196584108},
{"learn":[2.951698547],"iteration":1,"passed_time":0.001497664874,"remaining_time":0.7473347721},
{"learn":[2.884307657],"iteration":2,"passed_time":0.001733171144,"remaining_time":0.5759905435},
{"learn":[2.813809539],"iteration":3,"passed_time":0.002139598631,"remaining_time":0.5327600592},
{"learn":[2.754060176],"iteration":4,"passed_time":0.002379605021,"remaining_time":0.4735413993},
{"learn":[2.693081811],"iteration":5,"passed_time":0.002651445592,"remaining_time":0.4392561531},
{"learn":[2.635192216],"iteration":6,"passed_time":0.002966495647,"remaining_time":0.4208185968},
{"learn":[2.57802465],"iteration":7,"passed_time":0.003214627253,"remaining_time":0.3986137794},
{"learn":[2.521953753],"iteration":8,"passed_time":0.0036858898,"remaining_time":0.4058574213},
{"learn":[2.465664598],"iteration":9,"passed_time":0.004083692058,"remaining_time":0.4042855137},
{"learn":[2.414158013],"iteration":10,"passed_time":0.004478827578,"remaining_time":0.4026873159},
{"learn":[2.368299719],"iteration":11,"passed_time":0.004844337309,"remaining_time":0.3988504385},
{"learn":[2.319348081],"iteration":12,"passed_time":0.005028758886,"remaining_time":0.3817988477},
{"learn":[2.26753575],"iteration":13,"passed_time":0.005295432653,"remaining_time":0.3729497568},
{"learn":[2.21903177],"iteration":14,"passed_time":0.005527355494,"remaining_time":0.3629630108},
{"learn":[2.170897635],"iteration":15,"passed_time":0.005745236295,"remaining_time":0.3533320321},
{"learn":[2.121945069],"iteration":16,"passed_time":0.005947950025,"remaining_time":0.3439314632},
{"learn":[2.076985695],"iteration":17,"passed_time":0.006976810751,"remaining_time":0.3806237865},
{"learn":[2.031972279],"iteration":18,"passed_time":0.0071977333,"remaining_time":0.3716303351},
{"learn":[1.988818295],"iteration":19,"passed_time":0.007445989909,"remaining_time":0.3648535056},
{"learn":[1.946293282],"iteration":20,"passed_time":0.007696621582,"remaining_time":0.358809168},
{"learn":[1.918996283],"iteration":21,"passed_time":0.007758373226,"remaining_time":0.3448949552},
{"learn":[1.883484985],"iteration":22,"passed_time":0.007855417477,"remaining_time":0.3336844728},
{"learn":[1.841849461],"iteration":23,"passed_time":0.008194343167,"remaining_time":0.3332366221},
{"learn":[1.805064478],"iteration":24,"passed_time":0.008425432653,"remaining_time":0.3285918735},
{"learn":[1.769078219],"iteration":25,"passed_time":0.008623687931,"remaining_time":0.3230566171},
{"learn":[1.736705223],"iteration":26,"passed_time":0.008824484944,"remaining_time":0.3180082907},
{"learn":[1.704063226],"iteration":27,"passed_time":0.009063449639,"remaining_time":0.3146311803},
{"learn":[1.671701599],"iteration":28,"passed_time":0.009295664155,"remaining_time":0.3112444791},
{"learn":[1.641308312],"iteration":29,"passed_time":0.009484335845,"remaining_time":0.3066601923},
{"learn":[1.612285681],"iteration":30,"passed_time":0.009668965761,"remaining_time":0.3022331555},
{"learn":[1.580200452],"iteration":31,"passed_time":0.009860220853,"remaining_time":0.2982716808},
{"learn":[1.551637492],"iteration":32,"passed_time":0.01004680915,"remaining_time":0.2944019531},
{"learn":[1.518785284],"iteration":33,"passed_time":0.01036819271,"remaining_time":0.2945786517},
{"learn":[1.49163292],"iteration":34,"passed_time":0.01056807303,"remaining_time":0.2913768707},
{"learn":[1.462766619],"iteration":35,"passed_time":0.01075382798,"remaining_time":0.2879636158},
{"learn":[1.437645666],"iteration":36,"passed_time":0.01097883397,"remaining_time":0.2857464084},
{"learn":[1.415021412],"iteration":37,"passed_time":0.01118350608,"remaining_time":0.2831192856},
{"learn":[1.396125477],"iteration":38,"passed_time":0.01129830081,"remaining_time":0.2784017199},
{"learn":[1.371822854],"iteration":39,"passed_time":0.01157180809,"remaining_time":0.2777233941},
{"learn":[1.349770794],"iteration":40,"passed_time":0.01174735443,"remaining_time":0.2747734853},
{"learn":[1.329380491],"iteration":41,"passed_time":0.01197402713,"remaining_time":0.2731218569},
{"learn":[1.30730783],"iteration":42,"passed_time":0.0122108251,"remaining_time":0.2717618517},
{"learn":[1.287521697],"iteration":43,"passed_time":0.01244245627,"remaining_time":0.2703406407},
{"learn":[1.267656492],"iteration":44,"passed_time":0.01263441971,"remaining_time":0.2681304628},
{"learn":[1.250583393],"iteration":45,"passed_time":0.01283800847,"remaining_time":0.2662491321},
{"learn":[1.231977568],"iteration":46,"passed_time":0.01318339266,"remaining_time":0.2673143236},
{"learn":[1.214350583],"iteration":47,"passed_time":0.01342252403,"remaining_time":0.2662133932},
{"learn":[1.196015423],"iteration":48,"passed_time":0.0137207403,"remaining_time":0.2662943679},
{"learn":[1.178659597],"iteration":49,"passed_time":0.01396187172,"remaining_time":0.2652755627},
{"learn":[1.161932234],"iteration":50,"passed_time":0.01423871243,"remaining_time":0.2649517273},
{"learn":[1.149629071],"iteration":51,"passed_time":0.0144367177,"remaining_time":0.2631924688},
{"learn":[1.132908342],"iteration":52,"passed_time":0.01462426436,"remaining_time":0.2613052518},
{"learn":[1.118255055],"iteration":53,"passed_time":0.01492110559,"remaining_time":0.2613956647},
{"learn":[1.102754148],"iteration":54,"passed_time":0.0150677345,"remaining_time":0.2588910746},
{"learn":[1.087299418],"iteration":55,"passed_time":0.01538145118,"remaining_time":0.2592873199},
{"learn":[1.072153256],"iteration":56,"passed_time":0.01556891451,"remaining_time":0.2575699365},
{"learn":[1.0585295],"iteration":57,"passed_time":0.01575450278,"remaining_time":0.2558748555},
{"learn":[1.042945691],"iteration":58,"passed_time":0.01600892622,"remaining_time":0.2553288064},
{"learn":[1.029722938],"iteration":59,"passed_time":0.01629997564,"remaining_time":0.255366285},
{"learn":[1.014754614],"iteration":60,"passed_time":0.01653785697,"remaining_time":0.2545745524},
{"learn":[1.003551184],"iteration":61,"passed_time":0.01678403019,"remaining_time":0.2539261342},
{"learn":[0.9908026633],"iteration":62,"passed_time":0.01701374464,"remaining_time":0.2530456941},
{"learn":[0.9788548825],"iteration":63,"passed_time":0.01733004473,"remaining_time":0.2534519042},
{"learn":[0.9692804094],"iteration":64,"passed_time":0.0174830488,"remaining_time":0.2514869328},
{"learn":[0.9585509346],"iteration":65,"passed_time":0.01773097207,"remaining_time":0.2509201199},
{"learn":[0.9485152151],"iteration":66,"passed_time":0.01799297905,"remaining_time":0.250558947},
{"learn":[0.9401970887],"iteration":67,"passed_time":0.0182816534,"remaining_time":0.2505661907},
{"learn":[0.9298504739],"iteration":68,"passed_time":0.01846278322,"remaining_time":0.2491137852},
{"learn":[0.9231841385],"iteration":69,"passed_time":0.01853836857,"remaining_time":0.2462954681},
{"learn":[0.9132490714],"iteration":70,"passed_time":0.01921284486,"remaining_time":0.2513906038},
{"learn":[0.9042862548],"iteration":71,"passed_time":0.01962368913,"remaining_time":0.2529275488},
{"learn":[0.8961052945],"iteration":72,"passed_time":0.01994632272,"remaining_time":0.2532909748},
{"learn":[0.8893643501],"iteration":73,"passed_time":0.02017749554,"remaining_time":0.2524913631},
{"learn":[0.8811809702],"iteration":74,"passed_time":0.02036950065,"remaining_time":0.2512238414},
{"learn":[0.8728826944],"iteration":75,"passed_time":0.02055142216,"remaining_time":0.2498620273},
{"learn":[0.8635608791],"iteration":76,"passed_time":0.02073701044,"remaining_time":0.2485748134},
{"learn":[0.8543518141],"iteration":77,"passed_time":0.02099239224,"remaining_time":0.2481408416},
{"learn":[0.8453786149],"iteration":78,"passed_time":0.02168891078,"remaining_time":0.2528542637},
{"learn":[0.8369472014],"iteration":79,"passed_time":0.02188291595,"remaining_time":0.2516535334},
{"learn":[0.8280378359],"iteration":80,"passed_time":0.02223317527,"remaining_time":0.25225047},
{"learn":[0.8218851507],"iteration":81,"passed_time":0.02246905655,"remaining_time":0.2515438282},
{"learn":[0.8134295226],"iteration":82,"passed_time":0.02276468942,"remaining_time":0.2515086771},
{"learn":[0.8047485969],"iteration":83,"passed_time":0.02295431947,"remaining_time":0.2503113885},
{"learn":[0.7972538246],"iteration":84,"passed_time":0.02313574097,"remaining_time":0.2490494469},
{"learn":[0.7897088143],"iteration":85,"passed_time":0.02337399731,"remaining_time":0.2484166691},
{"learn":[0.784073705],"iteration":86,"passed_time":0.02365958825,"remaining_time":0.248289702},
{"learn":[0.7781350681],"iteration":87,"passed_time":0.02394767925,"remaining_time":0.2481850395},
{"learn":[0.770290764],"iteration":88,"passed_time":0.02422793671,"remaining_time":0.2479960713},
{"learn":[0.7638843071],"iteration":89,"passed_time":0.02471636638,"remaining_time":0.2499099268},
{"learn":[0.7581729943],"iteration":90,"passed_time":0.02515071128,"remaining_time":0.2512307314},
{"learn":[0.7521187305],"iteration":91,"passed_time":0.02542876035,"remaining_time":0.2509708087},
{"learn":[0.7451542627],"iteration":92,"passed_time":0.02573147674,"remaining_time":0.2509510689},
{"learn":[0.7400495949],"iteration":93,"passed_time":0.02627524122,"remaining_time":0.2532486016},
{"learn":[0.7350449886],"iteration":94,"passed_time":0.02648449679,"remaining_time":0.25229968},
{"learn":[0.7302318218],"iteration":95,"passed_time":0.02682396416,"remaining_time":0.2525923292},
{"learn":[0.7249016069],"iteration":96,"passed_time":0.02714238931,"remaining_time":0.2526760572},
{"learn":[0.7187776519],"iteration":97,"passed_time":0.02760377659,"remaining_time":0.2540674131},
{"learn":[0.714439501],"iteration":98,"passed_time":0.02789149258,"remaining_time":0.2538407557},
{"learn":[0.7098856291],"iteration":99,"passed_time":0.02816708326,"remaining_time":0.2535037493},
{"learn":[0.7042396899],"iteration":100,"passed_time":0.02838654743,"remaining_time":0.2526683776},
{"learn":[0.6987936834],"iteration":101,"passed_time":0.02867497178,"remaining_time":0.2524522025},
{"learn":[0.6947559425],"iteration":102,"passed_time":0.02897972989,"remaining_time":0.252376871},
{"learn":[0.689091582],"iteration":103,"passed_time":0.02924469528,"remaining_time":0.2519542978},
{"learn":[0.6853761255],"iteration":104,"passed_time":0.02942236668,"remaining_time":0.2507906493},
{"learn":[0.6824909656],"iteration":105,"passed_time":0.02954945339,"remaining_time":0.2492189748},
{"learn":[0.6774923757],"iteration":106,"passed_time":0.02981350209,"remaining_time":0.2488173586},
{"learn":[0.6749147336],"iteration":107,"passed_time":0.02993571368,"remaining_time":0.2472468204},
{"learn":[0.6720291363],"iteration":108,"passed_time":0.0300792175,"remaining_time":0.2458769063},
{"learn":[0.6677594249],"iteration":109,"passed_time":0.03027801446,"remaining_time":0.2449766624},
{"learn":[0.6643661374],"iteration":110,"passed_time":0.03055281344,"remaining_time":0.2446977581},
{"learn":[0.6596473735],"iteration":111,"passed_time":0.03074665193,"remaining_time":0.2437770261},
{"learn":[0.6569093718],"iteration":112,"passed_time":0.03099911699,"remaining_time":0.2433293519},
{"learn":[0.6521170735],"iteration":113,"passed_time":0.031275041,"remaining_time":0.2430674239},
{"learn":[0.6477420138],"iteration":114,"passed_time":0.03154758993,"remaining_time":0.242779279},
{"learn":[0.6445703035],"iteration":115,"passed_time":0.0317518037,"remaining_time":0.241970642},
{"learn":[0.6410694023],"iteration":116,"passed_time":0.03202181088,"remaining_time":0.2416688804},
{"learn":[0.6371811353],"iteration":117,"passed_time":0.03234927794,"remaining_time":0.2417971453},
{"learn":[0.6334934134],"iteration":118,"passed_time":0.03260040962,"remaining_time":0.2413526124},
{"learn":[0.6296768032],"iteration":119,"passed_time":0.03287929205,"remaining_time":0.2411148083},
{"learn":[0.6262936061],"iteration":120,"passed_time":0.03310829814,"remaining_time":0.2405140006},
{"learn":[0.6232453497],"iteration":121,"passed_time":0.03337672196,"remaining_time":0.2402029662},
{"learn":[0.6203452453],"iteration":122,"passed_time":0.03363443715,"remaining_time":0.2398162714},
{"learn":[0.6171439635],"iteration":123,"passed_time":0.03396090418,"remaining_time":0.2399173553},
{"learn":[0.6140881139],"iteration":124,"passed_time":0.03419628544,"remaining_time":0.2393739981},
{"learn":[0.610766734],"iteration":125,"passed_time":0.03451662731,"remaining_time":0.2394248593},
{"learn":[0.6084452915],"iteration":126,"passed_time":0.03475930043,"remaining_time":0.2389359786},
{"learn":[0.6053682431],"iteration":127,"passed_time":0.03497559786,"remaining_time":0.2382712604},
{"learn":[0.6025986387],"iteration":128,"passed_time":0.03518552012,"remaining_time":0.2375704498},
{"learn":[0.5998655798],"iteration":129,"passed_time":0.03538581711,"remaining_time":0.2368127761},
{"learn":[0.5977010015],"iteration":130,"passed_time":0.03567415812,"remaining_time":0.2366476596},
{"learn":[0.5947265218],"iteration":131,"passed_time":0.03593554008,"remaining_time":0.2363033999},
{"learn":[0.5925064016],"iteration":132,"passed_time":0.03619950544,"remaining_time":0.2359772272},
{"learn":[0.5903657199],"iteration":133,"passed_time":0.03639009385,"remaining_time":0.2351777707},
{"learn":[0.5886555337],"iteration":134,"passed_time":0.03663701709,"remaining_time":0.2347482947},
{"learn":[0.5854768144],"iteration":135,"passed_time":0.03688056524,"remaining_time":0.2343000616},
{"learn":[0.5835177144],"iteration":136,"passed_time":0.03711332144,"remaining_time":0.2337868351},
{"learn":[0.5806589213],"iteration":137,"passed_time":0.0374247464,"remaining_time":0.2337690681},
{"learn":[0.5779303895],"iteration":138,"passed_time":0.03772687944,"remaining_time":0.2336895194},
{"learn":[0.5751764423],"iteration":139,"passed_time":0.03808801406,"remaining_time":0.2339692292},
{"learn":[0.5728318882],"iteration":140,"passed_time":0.03830185308,"remaining_time":0.233342495},
{"learn":[0.5697148589],"iteration":141,"passed_time":0.03852048391,"remaining_time":0.2327505295},
{"learn":[0.5673023223],"iteration":142,"passed_time":0.03871236401,"remaining_time":0.2320034683},
{"learn":[0.5647549684],"iteration":143,"passed_time":0.03898332956,"remaining_time":0.2317342368},
{"learn":[0.5619598238],"iteration":144,"passed_time":0.03933646396,"remaining_time":0.2319494944},
{"learn":[0.5596675331],"iteration":145,"passed_time":0.040327032,"remaining_time":0.235885516},
{"learn":[0.5572903854],"iteration":146,"passed_time":0.0405722052,"remaining_time":0.2354291907},
{"learn":[0.5560550489],"iteration":147,"passed_time":0.04075458505,"remaining_time":0.2346142329},
{"learn":[0.5529714882],"iteration":148,"passed_time":0.04095442371,"remaining_time":0.2339074804},
{"learn":[0.5506769305],"iteration":149,"passed_time":0.04126647368,"remaining_time":0.2338433509},
{"learn":[0.5487909863],"iteration":150,"passed_time":0.04152848066,"remaining_time":0.2334945701},
{"learn":[0.5468977797],"iteration":151,"passed_time":0.04175894513,"remaining_time":0.232970957},
{"learn":[0.5454389578],"iteration":152,"passed_time":0.04196232554,"remaining_time":0.2323012401},
{"learn":[0.5437547957],"iteration":153,"passed_time":0.04214512207,"remaining_time":0.2315245018},
{"learn":[0.5423857998],"iteration":154,"passed_time":0.04228541748,"remaining_time":0.2305237275},
{"learn":[0.5401403531],"iteration":155,"passed_time":0.04249642309,"remaining_time":0.2299165455},
{"learn":[0.5376740991],"iteration":156,"passed_time":0.0427370545,"remaining_time":0.2294734837},
{"learn":[0.5355088596],"iteration":157,"passed_time":0.04292576786,"remaining_time":0.2287563072},
{"learn":[0.5330713873],"iteration":158,"passed_time":0.04311577292,"remaining_time":0.2280526102},
{"learn":[0.5310585138],"iteration":159,"passed_time":0.04335486262,"remaining_time":0.2276130287},
{"learn":[0.5293196577],"iteration":160,"passed_time":0.04357795189,"remaining_time":0.2270925567},
{"learn":[0.5273217447],"iteration":161,"passed_time":0.04379370763,"remaining_time":0.226537821},
{"learn":[0.5248070785],"iteration":162,"passed_time":0.04404213091,"remaining_time":0.2261549913},
{"learn":[0.5232686723],"iteration":163,"passed_time":0.04423517772,"remaining_time":0.2254915157},
{"learn":[0.5211647447],"iteration":164,"passed_time":0.04442064099,"remaining_time":0.224795365},
{"learn":[0.5196299021],"iteration":165,"passed_time":0.04471194041,"remaining_time":0.2246370982},
{"learn":[0.5178821918],"iteration":166,"passed_time":0.04492573777,"remaining_time":0.2240906561},
{"learn":[0.5158040477],"iteration":167,"passed_time":0.04517374438,"remaining_time":0.2237175912},
{"learn":[0.5145378256],"iteration":168,"passed_time":0.04536199939,"remaining_time":0.2230521982},
{"learn":[0.5121757682],"iteration":169,"passed_time":0.0456177562,"remaining_time":0.2227219861},
{"learn":[0.5109039334],"iteration":170,"passed_time":0.04601030831,"remaining_time":0.2230558222},
{"learn":[0.508992071],"iteration":171,"passed_time":0.04618756303,"remaining_time":0.2223447802},
{"learn":[0.5077746855],"iteration":172,"passed_time":0.04655728121,"remaining_time":0.2225599512},
{"learn":[0.5053839048],"iteration":173,"passed_time":0.04687233127,"remaining_time":0.2225088829},
{"learn":[0.5031405789],"iteration":174,"passed_time":0.04716742246,"remaining_time":0.2223607059},
{"learn":[0.5010137721],"iteration":175,"passed_time":0.0474707222,"remaining_time":0.2222492903},
{"learn":[0.4996959602],"iteration":176,"passed_time":0.04778910567,"remaining_time":0.2222058416},
{"learn":[0.4984335149],"iteration":177,"passed_time":0.0480982389,"remaining_time":0.2221165864},
{"learn":[0.4972339522],"iteration":178,"passed_time":0.04840403871,"remaining_time":0.2220095854},
{"learn":[0.4956924183],"iteration":179,"passed_time":0.04869975492,"remaining_time":0.2218544391},
{"learn":[0.4940491438],"iteration":180,"passed_time":0.04911134921,"remaining_time":0.2222220718},
{"learn":[0.4926418516],"iteration":181,"passed_time":0.04930877113,"remaining_time":0.2216185428},
{"learn":[0.4914834077],"iteration":182,"passed_time":0.04949194268,"remaining_time":0.2209558315},
{"learn":[0.4904456881],"iteration":183,"passed_time":0.04967065577,"remaining_time":0.2202785604},
{"learn":[0.4890947031],"iteration":184,"passed_time":0.04985316063,"remaining_time":0.2196233833},
{"learn":[0.4872797445],"iteration":185,"passed_time":0.05003512381,"remaining_time":0.2189709182},
{"learn":[0.486406526],"iteration":186,"passed_time":0.05021108682,"remaining_time":0.2182973989},
{"learn":[0.4853620337],"iteration":187,"passed_time":0.05038984158,"remaining_time":0.2176412307},
{"learn":[0.4844990755],"iteration":188,"passed_time":0.05051271985,"remaining_time":0.2167503482},
{"learn":[0.4834448497],"iteration":189,"passed_time":0.0506898079,"remaining_time":0.2160986547},
{"learn":[0.4826080776],"iteration":190,"passed_time":0.05086885434,"remaining_time":0.215460226},
{"learn":[0.4806293941],"iteration":191,"passed_time":0.05105065084,"remaining_time":0.2148381556},
{"learn":[0.4797880683],"iteration":192,"passed_time":0.05122653053,"remaining_time":0.2141959074},
{"learn":[0.4782587006],"iteration":193,"passed_time":0.05140266021,"remaining_time":0.2135595058},
{"learn":[0.4771868454],"iteration":194,"passed_time":0.05157774821,"remaining_time":0.2129235247},
{"learn":[0.4763303179],"iteration":195,"passed_time":0.0517500028,"remaining_time":0.2122806237},
{"learn":[0.47465029],"iteration":196,"passed_time":0.05192346575,"remaining_time":0.2116474264},
{"learn":[0.473966846],"iteration":197,"passed_time":0.05209701203,"remaining_time":0.2110192104},
{"learn":[0.4729948323],"iteration":198,"passed_time":0.05227130834,"remaining_time":0.2103985828},
{"learn":[0.472183273],"iteration":199,"passed_time":0.05244547965,"remaining_time":0.2097819186},
{"learn":[0.4704054822],"iteration":200,"passed_time":0.05261940094,"remaining_time":0.2091686634},
{"learn":[0.4695610643],"iteration":201,"passed_time":0.05279219721,"remaining_time":0.2085553137},
{"learn":[0.4681364964],"iteration":202,"passed_time":0.05296570183,"remaining_time":0.2079490855},
{"learn":[0.466354164],"iteration":203,"passed_time":0.05313703972,"remaining_time":0.2073386452},
{"learn":[0.4651150443],"iteration":204,"passed_time":0.05331037767,"remaining_time":0.2067402451},
{"learn":[0.4638150873],"iteration":205,"passed_time":0.0534904658,"remaining_time":0.2061719895},
{"learn":[0.4631168188],"iteration":206,"passed_time":0.05366151202,"remaining_time":0.2055728456},
{"learn":[0.4621960658],"iteration":207,"passed_time":0.05383530831,"remaining_time":0.2049882894},
{"learn":[0.4606373026],"iteration":208,"passed_time":0.05400868793,"remaining_time":0.2044060869},
{"learn":[0.4596585231],"iteration":209,"passed_time":0.0541817342,"remaining_time":0.2038265239},
{"learn":[0.4584792993],"iteration":210,"passed_time":0.05435478048,"remaining_time":0.2032508142},
{"learn":[0.457155176],"iteration":211,"passed_time":0.05453232687,"remaining_time":0.2026956301},
{"learn":[0.4563352751],"iteration":212,"passed_time":0.05471103996,"remaining_time":0.2021483026},
{"learn":[0.45571358],"iteration":213,"passed_time":0.05488854469,"remaining_time":0.2015999819},
{"learn":[0.4546999107],"iteration":214,"passed_time":0.05506563274,"remaining_time":0.2010535893},
{"learn":[0.4526820951],"iteration":215,"passed_time":0.05524530419,"remaining_time":0.200519993},
{"learn":[0.4519065397],"iteration":216,"passed_time":0.05542247557,"remaining_time":0.1999806377},
{"learn":[0.4509623876],"iteration":217,"passed_time":0.05559477183,"remaining_time":0.1994271173},
{"learn":[0.4493657635],"iteration":218,"passed_time":0.05576677641,"remaining_time":0.1988760382},
{"learn":[0.4488061781],"iteration":219,"passed_time":0.05594036436,"remaining_time":0.1983340191},
{"learn":[0.4475190612],"iteration":220,"passed_time":0.05611991081,"remaining_time":0.1978163372},
{"learn":[0.4462584016],"iteration":221,"passed_time":0.05629570715,"remaining_time":0.1972885593},
{"learn":[0.444766907],"iteration":222,"passed_time":0.05647333688,"remaining_time":0.1967703263},
{"learn":[0.4437693771],"iteration":223,"passed_time":0.05665567507,"remaining_time":0.1962714458},
{"learn":[0.4430885553],"iteration":224,"passed_time":0.05682792966,"remaining_time":0.1957406466},
{"learn":[0.441709863],"iteration":225,"passed_time":0.05700147594,"remaining_time":0.1952174442},
{"learn":[0.4410671918],"iteration":226,"passed_time":0.05717818898,"remaining_time":0.1947081061},
{"learn":[0.4405285197],"iteration":227,"passed_time":0.05734981855,"remaining_time":0.1941844733},
{"learn":[0.4390952903],"iteration":228,"passed_time":0.05752415653,"remaining_time":0.1936730335},
{"learn":[0.4385999386],"iteration":229,"passed_time":0.05769932786,"remaining_time":0.193167315},
{"learn":[0.4380465906],"iteration":230,"passed_time":0.05789833316,"remaining_time":0.1927438017},
{"learn":[0.4375104211],"iteration":231,"passed_time":0.05806967105,"remaining_time":0.1922306352},
{"learn":[0.4369643216],"iteration":232,"passed_time":0.05824371735,"remaining_time":0.1917293185},
{"learn":[0.4363888461],"iteration":233,"passed_time":0.05841509691,"remaining_time":0.1912220694},
{"learn":[0.4354987086],"iteration":234,"passed_time":0.05858943489,"remaining_time":0.1907273093},
{"learn":[0.4346016565],"iteration":235,"passed_time":0.05876431455,"remaining_time":0.1902370183},
{"learn":[0.4338581779],"iteration":236,"passed_time":0.05893740249,"remaining_time":0.1897436207},
{"learn":[0.4324692098],"iteration":237,"passed_time":0.05911024042,"remaining_time":0.1892521143},
{"learn":[0.4314528081],"iteration":238,"passed_time":0.05928557842,"remaining_time":0.1887712351},
{"learn":[0.4301886987],"iteration":239,"passed_time":0.05945783301,"remaining_time":0.1882831379},
{"learn":[0.4289824212],"iteration":240,"passed_time":0.05963304601,"remaining_time":0.1878069789},
{"learn":[0.4284974061],"iteration":241,"passed_time":0.05980513392,"remaining_time":0.1873235187},
{"learn":[0.427387758],"iteration":242,"passed_time":0.05998080527,"remaining_time":0.1868537843},
{"learn":[0.426141419],"iteration":243,"passed_time":0.06015568492,"remaining_time":0.1863840074},
{"learn":[0.4256870774],"iteration":244,"passed_time":0.06032881453,"remaining_time":0.1859112448},
{"learn":[0.4245538351],"iteration":245,"passed_time":0.06050011076,"remaining_time":0.1854352988},
{"learn":[0.4240980326],"iteration":246,"passed_time":0.060671782,"remaining_time":0.1849629629},
{"learn":[0.4233426593],"iteration":247,"passed_time":0.06084449493,"remaining_time":0.1844962104},
{"learn":[0.4216389906],"iteration":248,"passed_time":0.06101574949,"remaining_time":0.1840274211},
{"learn":[0.420491457],"iteration":249,"passed_time":0.06326685109,"remaining_time":0.1898005533},
{"learn":[0.4193882429],"iteration":250,"passed_time":0.06370086264,"remaining_time":0.1900874347},
{"learn":[0.4190379916],"iteration":251,"passed_time":0.06406616404,"remaining_time":0.1901646456},
{"learn":[0.4186266168],"iteration":252,"passed_time":0.06435829681,"remaining_time":0.190022323},
{"learn":[0.4170432528],"iteration":253,"passed_time":0.06458042773,"remaining_time":0.1896732247},
{"learn":[0.4164742771],"iteration":254,"passed_time":0.06477034945,"remaining_time":0.1892310209},
{"learn":[0.4157750732],"iteration":255,"passed_time":0.06495281264,"remaining_time":0.1887691117},
{"learn":[0.4152590285],"iteration":256,"passed_time":0.06514823451,"remaining_time":0.1883468414},
{"learn":[0.4145993703],"iteration":257,"passed_time":0.06533311443,"remaining_time":0.1878960113},
{"learn":[0.4136820382],"iteration":258,"passed_time":0.06551628598,"remaining_time":0.1874423471},
{"learn":[0.4126104066],"iteration":259,"passed_time":0.0656963741,"remaining_time":0.1869819878},
{"learn":[0.4119597632],"iteration":260,"passed_time":0.06587175377,"remaining_time":0.1865104446},
{"learn":[0.4102903816],"iteration":261,"passed_time":0.06605205024,"remaining_time":0.1860550117},
{"learn":[0.4092841899],"iteration":262,"passed_time":0.06623001331,"remaining_time":0.1855951324},
{"learn":[0.4085717708],"iteration":263,"passed_time":0.06640918475,"remaining_time":0.1851407575},
{"learn":[0.4071365436],"iteration":264,"passed_time":0.06658364773,"remaining_time":0.1846754003},
{"learn":[0.4062178329],"iteration":265,"passed_time":0.0667578607,"remaining_time":0.1842115404},
{"learn":[0.4056824113],"iteration":266,"passed_time":0.06693557376,"remaining_time":0.1837594591},
{"learn":[0.4052750231],"iteration":267,"passed_time":0.06710928672,"remaining_time":0.1832984996},
{"learn":[0.4045606295],"iteration":268,"passed_time":0.06728666644,"remaining_time":0.18284964},
{"learn":[0.4042346534],"iteration":269,"passed_time":0.06746033774,"remaining_time":0.182392765},
{"learn":[0.4033621629],"iteration":270,"passed_time":0.0676366341,"remaining_time":0.1819450415},
{"learn":[0.4024709175],"iteration":271,"passed_time":0.0678145555,"remaining_time":0.1815036632},
{"learn":[0.4019537852],"iteration":272,"passed_time":0.06798810179,"remaining_time":0.1810525641},
{"learn":[0.4012251577],"iteration":273,"passed_time":0.06816593985,"remaining_time":0.1806148625},
{"learn":[0.4007189535],"iteration":274,"passed_time":0.06834119452,"remaining_time":0.1801722401},
{"learn":[0.4002561422],"iteration":275,"passed_time":0.06851465747,"remaining_time":0.1797268551},
{"learn":[0.399572465],"iteration":276,"passed_time":0.08030588807,"remaining_time":0.2096070652},
{"learn":[0.3990785018],"iteration":277,"passed_time":0.0805974375,"remaining_time":0.2093214024},
{"learn":[0.3981470682],"iteration":278,"passed_time":0.08079244269,"remaining_time":0.2087862049},
{"learn":[0.3977293699],"iteration":279,"passed_time":0.08097869765,"remaining_time":0.2082309368},
{"learn":[0.3972488793],"iteration":280,"passed_time":0.08116261921,"remaining_time":0.2076723246},
{"learn":[0.3966854109],"iteration":281,"passed_time":0.08134316569,"remaining_time":0.2071077765},
{"learn":[0.395482562],"iteration":282,"passed_time":0.08152487886,"remaining_time":0.206548898},
{"learn":[0.394672264],"iteration":283,"passed_time":0.08171392556,"remaining_time":0.2060111644},
{"learn":[0.3940430953],"iteration":284,"passed_time":0.08189526372,"remaining_time":0.2054565388},
{"learn":[0.3933218407],"iteration":285,"passed_time":0.08207301845,"remaining_time":0.2048955775},
{"learn":[0.3928627173],"iteration":286,"passed_time":0.08225335659,"remaining_time":0.2043437047},
{"learn":[0.3925356384],"iteration":287,"passed_time":0.08243069464,"remaining_time":0.2037869951},
{"learn":[0.3911756313],"iteration":288,"passed_time":0.08260740768,"remaining_time":0.2032313732},
{"learn":[0.3904279992],"iteration":289,"passed_time":0.08278482907,"remaining_time":0.2026800988},
{"learn":[0.3895872044],"iteration":290,"passed_time":0.08296070875,"remaining_time":0.2021276375},
{"learn":[0.389030647],"iteration":291,"passed_time":0.08313492172,"remaining_time":0.2015737143},
{"learn":[0.3884922353],"iteration":292,"passed_time":0.08331680157,"remaining_time":0.201040883},
{"learn":[0.3880802648],"iteration":293,"passed_time":0.08348922282,"remaining_time":0.2004877256},
{"learn":[0.387821342],"iteration":294,"passed_time":0.08455545954,"remaining_time":0.2020732169},
{"learn":[0.3867491241],"iteration":295,"passed_time":0.08486350941,"remaining_time":0.2018375359},
{"learn":[0.3859978151],"iteration":296,"passed_time":0.08516022564,"remaining_time":0.2015745408},
{"learn":[0.3851747056],"iteration":297,"passed_time":0.08556515309,"remaining_time":0.2015662331},
{"learn":[0.3844590216],"iteration":298,"passed_time":0.08604891597,"remaining_time":0.2017401007},
{"learn":[0.3839113127],"iteration":299,"passed_time":0.08624992132,"remaining_time":0.2012498164},
{"learn":[0.3827702277],"iteration":300,"passed_time":0.08643075947,"remaining_time":0.2007146208},
{"learn":[0.3824418045],"iteration":301,"passed_time":0.08660488911,"remaining_time":0.2001662669},
{"learn":[0.3821267162],"iteration":302,"passed_time":0.08677785205,"remaining_time":0.1996176993},
{"learn":[0.3813432714],"iteration":303,"passed_time":0.08695706515,"remaining_time":0.1990859123},
{"learn":[0.3808185736],"iteration":304,"passed_time":0.08713440321,"remaining_time":0.1985521647},
{"learn":[0.3804982877],"iteration":305,"passed_time":0.08747632898,"remaining_time":0.1983940272},
{"learn":[0.3799701316],"iteration":306,"passed_time":0.08769733486,"remaining_time":0.1979617363},
{"learn":[0.3795740977],"iteration":307,"passed_time":0.08806980311,"remaining_time":0.1978711161},
{"learn":[0.3793452621],"iteration":308,"passed_time":0.08826685002,"remaining_time":0.1973863863},
{"learn":[0.3785863318],"iteration":309,"passed_time":0.08846406361,"remaining_time":0.1969038835},
{"learn":[0.3783262424],"iteration":310,"passed_time":0.08874532109,"remaining_time":0.1966094091},
{"learn":[0.3776919267],"iteration":311,"passed_time":0.08907249647,"remaining_time":0.1964162743},
{"learn":[0.3773016956],"iteration":312,"passed_time":0.08948321574,"remaining_time":0.1964056524},
{"learn":[0.3769388953],"iteration":313,"passed_time":0.08976030645,"remaining_time":0.1961005421},
{"learn":[0.3760834321],"iteration":314,"passed_time":0.08999443768,"remaining_time":0.1957021899},
{"learn":[0.3754777062],"iteration":315,"passed_time":0.09024323598,"remaining_time":0.1953366247},
{"learn":[0.3751220103],"iteration":316,"passed_time":0.09052391011,"remaining_time":0.1950404751},
{"learn":[0.3744577074],"iteration":317,"passed_time":0.09081608456,"remaining_time":0.194769087},
{"learn":[0.3740046932],"iteration":318,"passed_time":0.09117601081,"remaining_time":0.1946422049},
{"learn":[0.3733554512],"iteration":319,"passed_time":0.0915975637,"remaining_time":0.1946448229},
{"learn":[0.3726930091],"iteration":320,"passed_time":0.09204957573,"remaining_time":0.1947092272},
{"learn":[0.3723909255],"iteration":321,"passed_time":0.09224970606,"remaining_time":0.1942400643},
{"learn":[0.3722598223],"iteration":322,"passed_time":0.0924287525,"remaining_time":0.193728376},
{"learn":[0.3720939512],"iteration":323,"passed_time":0.09260696557,"remaining_time":0.1932170022},
{"learn":[0.3718121691],"iteration":324,"passed_time":0.09279238718,"remaining_time":0.1927226503},
{"learn":[0.3714989693],"iteration":325,"passed_time":0.0929658918,"remaining_time":0.1922055554},
{"learn":[0.3712261226],"iteration":326,"passed_time":0.09316973056,"remaining_time":0.1917529929},
{"learn":[0.3706473021],"iteration":327,"passed_time":0.09334806864,"remaining_time":0.1912497016},
{"learn":[0.3699505899],"iteration":328,"passed_time":0.09352936513,"remaining_time":0.1907544195},
{"learn":[0.369865059],"iteration":329,"passed_time":0.09370678652,"remaining_time":0.1902531726},
{"learn":[0.3696595426],"iteration":330,"passed_time":0.09388891637,"remaining_time":0.189763399},
{"learn":[0.3689985985],"iteration":331,"passed_time":0.09406833782,"remaining_time":0.1892700291},
{"learn":[0.3688559177],"iteration":332,"passed_time":0.09424396749,"remaining_time":0.1887709499},
{"learn":[0.3686786239],"iteration":333,"passed_time":0.09442030552,"remaining_time":0.18827522},
{"learn":[0.3680615513],"iteration":334,"passed_time":0.09460697716,"remaining_time":0.1878019099},
{"learn":[0.3678530703],"iteration":335,"passed_time":0.09492586065,"remaining_time":0.1875915818},
{"learn":[0.367643579],"iteration":336,"passed_time":0.0953435801,"remaining_time":0.1875750552},
{"learn":[0.3674332076],"iteration":337,"passed_time":0.09564625483,"remaining_time":0.1873308305},
{"learn":[0.3668247296],"iteration":338,"passed_time":0.09598076373,"remaining_time":0.1871483328},
{"learn":[0.366363591],"iteration":339,"passed_time":0.09629352206,"remaining_time":0.1869227193},
{"learn":[0.3658917968],"iteration":340,"passed_time":0.0966119472,"remaining_time":0.1867075461},
{"learn":[0.3654798381],"iteration":341,"passed_time":0.09702895831,"remaining_time":0.1866814461},
{"learn":[0.3650256186],"iteration":342,"passed_time":0.0973945097,"remaining_time":0.1865544982},
{"learn":[0.3645884081],"iteration":343,"passed_time":0.09770001784,"remaining_time":0.1863116619},
{"learn":[0.3643370996],"iteration":344,"passed_time":0.09797919194,"remaining_time":0.1860184659},
{"learn":[0.3640753588],"iteration":345,"passed_time":0.09826028276,"remaining_time":0.1857289738},
{"learn":[0.3638823934],"iteration":346,"passed_time":0.09853737347,"remaining_time":0.1854320025},
{"learn":[0.3637172771],"iteration":347,"passed_time":0.09881946431,"remaining_time":0.1851445136},
{"learn":[0.363407944],"iteration":348,"passed_time":0.09910809699,"remaining_time":0.1848692583},
{"learn":[0.3632442449],"iteration":349,"passed_time":0.09942481376,"remaining_time":0.1846460827},
{"learn":[0.3629962149],"iteration":350,"passed_time":0.09983365798,"remaining_time":0.184592718},
{"learn":[0.362600614],"iteration":351,"passed_time":0.1001385411,"remaining_time":0.1843459507},
{"learn":[0.3625050224],"iteration":352,"passed_time":0.1004472576,"remaining_time":0.1841058802},
{"learn":[0.3623540761],"iteration":353,"passed_time":0.1007441822,"remaining_time":0.1838439031},
{"learn":[0.3619139109],"iteration":354,"passed_time":0.1010939832,"remaining_time":0.1836778005},
{"learn":[0.3613916717],"iteration":355,"passed_time":0.1013841159,"remaining_time":0.1834027266},
{"learn":[0.3609812624],"iteration":356,"passed_time":0.1016642484,"remaining_time":0.1831095566},
{"learn":[0.360735584],"iteration":357,"passed_time":0.1019358806,"remaining_time":0.1828012161},
{"learn":[0.360613351],"iteration":358,"passed_time":0.1022559725,"remaining_time":0.1825796054},
{"learn":[0.3600838072],"iteration":359,"passed_time":0.1024593112,"remaining_time":0.1821498866},
{"learn":[0.3597274821],"iteration":360,"passed_time":0.1027771113,"remaining_time":0.1819240281},
{"learn":[0.3595088412],"iteration":361,"passed_time":0.1030620356,"remaining_time":0.1816397202},
{"learn":[0.3593477052],"iteration":362,"passed_time":0.1033140006,"remaining_time":0.1812975714},
{"learn":[0.3592277087],"iteration":363,"passed_time":0.1042335251,"remaining_time":0.1821223131},
{"learn":[0.3590243396],"iteration":364,"passed_time":0.10454295,"remaining_time":0.1818760911},
{"learn":[0.3584963231],"iteration":365,"passed_time":0.104742122,"remaining_time":0.1814385392},
{"learn":[0.3584036978],"iteration":366,"passed_time":0.1050600888,"remaining_time":0.1812071831},
{"learn":[0.3578144532],"iteration":367,"passed_time":0.1053796806,"remaining_time":0.1809781472},
{"learn":[0.3576902702],"iteration":368,"passed_time":0.1056000198,"remaining_time":0.1805788957},
{"learn":[0.3575851114],"iteration":369,"passed_time":0.1059504458,"remaining_time":0.1804021105},
{"learn":[0.3573429468],"iteration":370,"passed_time":0.1062992468,"remaining_time":0.180221634},
{"learn":[0.3567734654],"iteration":371,"passed_time":0.1064980854,"remaining_time":0.1797870904},
{"learn":[0.3561768929],"iteration":372,"passed_time":0.1066845904,"remaining_time":0.1793330782},
{"learn":[0.356059824],"iteration":373,"passed_time":0.1069632645,"remaining_time":0.1790347689},
{"learn":[0.3557365817],"iteration":374,"passed_time":0.1072229797,"remaining_time":0.1787049662},
{"learn":[0.3552748111],"iteration":375,"passed_time":0.1074802782,"remaining_time":0.1783715256},
{"learn":[0.3549475202],"iteration":376,"passed_time":0.1077247431,"remaining_time":0.178017281},
{"learn":[0.3542996117],"iteration":377,"passed_time":0.1080352097,"remaining_time":0.1777722233},
{"learn":[0.3539447615],"iteration":378,"passed_time":0.1082376734,"remaining_time":0.1773498553},
{"learn":[0.3533906938],"iteration":379,"passed_time":0.1084531375,"remaining_time":0.1769498559},
{"learn":[0.3532817319],"iteration":380,"passed_time":0.1087047275,"remaining_time":0.1766095179},
{"learn":[0.3525637882],"iteration":381,"passed_time":0.1089486923,"remaining_time":0.1762573085},
{"learn":[0.3521908129],"iteration":382,"passed_time":0.1093556615,"remaining_time":0.1761682589},
{"learn":[0.3515752665],"iteration":383,"passed_time":0.10954825,"remaining_time":0.175733651},
{"learn":[0.3510848728],"iteration":384,"passed_time":0.1097469636,"remaining_time":0.1753100847},
{"learn":[0.3506730017],"iteration":385,"passed_time":0.1100217209,"remaining_time":0.1750086441},
{"learn":[0.3505413601],"iteration":386,"passed_time":0.1102470186,"remaining_time":0.1746289984},
{"learn":[0.3499329014],"iteration":387,"passed_time":0.1105639853,"remaining_time":0.1743947397},
{"learn":[0.3495232118],"iteration":388,"passed_time":0.1108718269,"remaining_time":0.1741457229},
{"learn":[0.3489785115],"iteration":389,"passed_time":0.1111187501,"remaining_time":0.173801122},
{"learn":[0.3485563579],"iteration":390,"passed_time":0.1113230472,"remaining_time":0.1733906285},
{"learn":[0.3477467801],"iteration":391,"passed_time":0.1115433031,"remaining_time":0.1730059395},
{"learn":[0.347524681],"iteration":392,"passed_time":0.1118504362,"remaining_time":0.1727562718},
{"learn":[0.3474193145],"iteration":393,"passed_time":0.1120794007,"remaining_time":0.1723860833},
{"learn":[0.3473199131],"iteration":394,"passed_time":0.1123439494,"remaining_time":0.1720711124},
{"learn":[0.3468077224],"iteration":395,"passed_time":0.1125630802,"remaining_time":0.1716871224},
{"learn":[0.3462583613],"iteration":396,"passed_time":0.1128330874,"remaining_time":0.1713812386},
{"learn":[0.3458416235],"iteration":397,"passed_time":0.1131591378,"remaining_time":0.1711603038},
{"learn":[0.3458044721],"iteration":398,"passed_time":0.1134228114,"remaining_time":0.1708448864},
{"learn":[0.3453483158],"iteration":399,"passed_time":0.1136552343,"remaining_time":0.1704828514},
{"learn":[0.3448554125],"iteration":400,"passed_time":0.1138866155,"remaining_time":0.1701199069},
{"learn":[0.344360704],"iteration":401,"passed_time":0.1141078713,"remaining_time":0.1697425549},
{"learn":[0.344149039],"iteration":402,"passed_time":0.1144080877,"remaining_time":0.1694829487},
{"learn":[0.3440856819],"iteration":403,"passed_time":0.1145999261,"remaining_time":0.1690632573},
{"learn":[0.3436453051],"iteration":404,"passed_time":0.1148669749,"remaining_time":0.1687551853},
{"learn":[0.3435392822],"iteration":405,"passed_time":0.1150884391,"remaining_time":0.1683806228},
{"learn":[0.3431884235],"iteration":406,"passed_time":0.1153680299,"remaining_time":0.168091503},
{"learn":[0.3427105465],"iteration":407,"passed_time":0.1156334536,"remaining_time":0.1677818739},
{"learn":[0.3422503701],"iteration":408,"passed_time":0.1158527928,"remaining_time":0.1674058693},
{"learn":[0.3420670622],"iteration":409,"passed_time":0.116086174,"remaining_time":0.1670508358},
{"learn":[0.3416299366],"iteration":410,"passed_time":0.1163158051,"remaining_time":0.16669102},
{"learn":[0.3412617365],"iteration":411,"passed_time":0.1165267691,"remaining_time":0.1663051947},
{"learn":[0.3411699736],"iteration":412,"passed_time":0.1167199409,"remaining_time":0.1658949281},
{"learn":[0.3410962309],"iteration":413,"passed_time":0.1170146987,"remaining_time":0.1656295011},
{"learn":[0.3406268282],"iteration":414,"passed_time":0.1172792891,"remaining_time":0.1653214076},
{"learn":[0.3404307602],"iteration":415,"passed_time":0.1175851306,"remaining_time":0.1650714333},
{"learn":[0.3399504856],"iteration":416,"passed_time":0.11787468,"remaining_time":0.1647984135},
{"learn":[0.3396163102],"iteration":417,"passed_time":0.1181982303,"remaining_time":0.1645726555},
{"learn":[0.3391723399],"iteration":418,"passed_time":0.1184550288,"remaining_time":0.1642538704},
{"learn":[0.3389752193],"iteration":419,"passed_time":0.1186679094,"remaining_time":0.1638747321},
{"learn":[0.3385254143],"iteration":420,"passed_time":0.1188844152,"remaining_time":0.1635013691},
{"learn":[0.3379967481],"iteration":421,"passed_time":0.1191383386,"remaining_time":0.1631799993},
{"learn":[0.3378037753],"iteration":422,"passed_time":0.1194426384,"remaining_time":0.1629276651},
{"learn":[0.3375753004],"iteration":423,"passed_time":0.1197229792,"remaining_time":0.1626425378},
{"learn":[0.3372970725],"iteration":424,"passed_time":0.1199728608,"remaining_time":0.1623162235},
{"learn":[0.3369903928],"iteration":425,"passed_time":0.1202376595,"remaining_time":0.1620103676},
{"learn":[0.3364628731],"iteration":426,"passed_time":0.1204804577,"remaining_time":0.1616751809},
{"learn":[0.3361278319],"iteration":427,"passed_time":0.1210146802,"remaining_time":0.1617298998},
{"learn":[0.3358908595],"iteration":428,"passed_time":0.1219279962,"remaining_time":0.1622864472},
{"learn":[0.3355589305],"iteration":429,"passed_time":0.122208837,"remaining_time":0.1619977607},
{"learn":[0.335174038],"iteration":430,"passed_time":0.1225919722,"remaining_time":0.1618441582},
{"learn":[0.334975057],"iteration":431,"passed_time":0.1227977277,"remaining_time":0.1614562716},
{"learn":[0.3348417456],"iteration":432,"passed_time":0.122997233,"remaining_time":0.1610610419},
{"learn":[0.3344095644],"iteration":433,"passed_time":0.1232153222,"remaining_time":0.1606909501},
{"learn":[0.3342322352],"iteration":434,"passed_time":0.1234712456,"remaining_time":0.1603706984},
{"learn":[0.3336852688],"iteration":435,"passed_time":0.1236705843,"remaining_time":0.1599775448},
{"learn":[0.3333654622],"iteration":436,"passed_time":0.1238912985,"remaining_time":0.159612817},
{"learn":[0.3331684207],"iteration":437,"passed_time":0.1241641808,"remaining_time":0.159315684},
{"learn":[0.3324416507],"iteration":438,"passed_time":0.1243986037,"remaining_time":0.158969514},
{"learn":[0.332027709],"iteration":439,"passed_time":0.1245959839,"remaining_time":0.1585767068},
{"learn":[0.331723809],"iteration":440,"passed_time":0.1248910751,"remaining_time":0.1583086417},
{"learn":[0.3313135111],"iteration":441,"passed_time":0.1251999167,"remaining_time":0.1580578133},
{"learn":[0.3307960128],"iteration":442,"passed_time":0.1254835075,"remaining_time":0.1577749745},
{"learn":[0.3304334377],"iteration":443,"passed_time":0.1256833879,"remaining_time":0.1573873055},
{"learn":[0.3300442866],"iteration":444,"passed_time":0.1259030604,"remaining_time":0.1570251652},
{"learn":[0.3297964361],"iteration":445,"passed_time":0.1261692341,"remaining_time":0.1567214254},
{"learn":[0.3294503874],"iteration":446,"passed_time":0.1264414914,"remaining_time":0.1564253797},
{"learn":[0.3291802139],"iteration":447,"passed_time":0.126690748,"remaining_time":0.1561011002},
{"learn":[0.3289173825],"iteration":448,"passed_time":0.1269592135,"remaining_time":0.1558007275},
{"learn":[0.3285679262],"iteration":449,"passed_time":0.1271979699,"remaining_time":0.1554641854},
{"learn":[0.328327968],"iteration":450,"passed_time":0.1274478932,"remaining_time":0.1551416704},
{"learn":[0.3277918345],"iteration":451,"passed_time":0.1276821911,"remaining_time":0.1548005326},
{"learn":[0.3277103299],"iteration":452,"passed_time":0.1279639903,"remaining_time":0.1545172244},
{"learn":[0.3275842338],"iteration":453,"passed_time":0.1281645373,"remaining_time":0.1541362056},
{"learn":[0.3273217334],"iteration":454,"passed_time":0.1285162133,"remaining_time":0.1539370027},
{"learn":[0.3271137628],"iteration":455,"passed_time":0.1288408886,"remaining_time":0.1537049197},
{"learn":[0.3266523761],"iteration":456,"passed_time":0.1290359355,"remaining_time":0.1533184091},
{"learn":[0.3264048183],"iteration":457,"passed_time":0.129254858,"remaining_time":0.1529609891},
{"learn":[0.3259576116],"iteration":458,"passed_time":0.1294497381,"remaining_time":0.1525758352},
{"learn":[0.3256816434],"iteration":459,"passed_time":0.1296624105,"remaining_time":0.1522123949},
{"learn":[0.3254714243],"iteration":460,"passed_time":0.1299008752,"remaining_time":0.1518797651},
{"learn":[0.3251555752],"iteration":461,"passed_time":0.1301200477,"remaining_time":0.1515250771},
{"learn":[0.3247227277],"iteration":462,"passed_time":0.1303199696,"remaining_time":0.1511486473},
{"learn":[0.3245450597],"iteration":463,"passed_time":0.1305299752,"remaining_time":0.1507846266},
{"learn":[0.3242428692],"iteration":464,"passed_time":0.1307346057,"remaining_time":0.150415084},
{"learn":[0.3238720646],"iteration":465,"passed_time":0.1310224884,"remaining_time":0.1501416497},
{"learn":[0.3234573446],"iteration":466,"passed_time":0.131284787,"remaining_time":0.1498389539},
{"learn":[0.3231937516],"iteration":467,"passed_time":0.1315330853,"remaining_time":0.1495205157},
{"learn":[0.3229030035],"iteration":468,"passed_time":0.1317390074,"remaining_time":0.1491543986},
{"learn":[0.3225450889],"iteration":469,"passed_time":0.1319286791,"remaining_time":0.1487706382},
{"learn":[0.3221938716],"iteration":470,"passed_time":0.132134518,"remaining_time":0.1484058599},
{"learn":[0.3219108567],"iteration":471,"passed_time":0.1323948582,"remaining_time":0.1481027228},
{"learn":[0.3216317455],"iteration":472,"passed_time":0.1326166975,"remaining_time":0.1477568701},
{"learn":[0.3212796496],"iteration":473,"passed_time":0.1328394534,"remaining_time":0.147412558},
{"learn":[0.3208595356],"iteration":474,"passed_time":0.1330271251,"remaining_time":0.1470299803},
{"learn":[0.3205239075],"iteration":475,"passed_time":0.1332646314,"remaining_time":0.1467030816},
{"learn":[0.3201153554],"iteration":476,"passed_time":0.133512638,"remaining_time":0.1463880706},
{"learn":[0.3199571605],"iteration":477,"passed_time":0.1337215185,"remaining_time":0.1460306123},
{"learn":[0.3198917],"iteration":478,"passed_time":0.1340598609,"remaining_time":0.1458145877},
{"learn":[0.3195882852],"iteration":479,"passed_time":0.1349713435,"remaining_time":0.1462189554},
{"learn":[0.3192770108],"iteration":480,"passed_time":0.1352428507,"remaining_time":0.1459273171},
{"learn":[0.3190014568],"iteration":481,"passed_time":0.1355156913,"remaining_time":0.1456371952},
{"learn":[0.3187939301],"iteration":482,"passed_time":0.1358126576,"remaining_time":0.1453729688},
{"learn":[0.3184748064],"iteration":483,"passed_time":0.1361839591,"remaining_time":0.1451878572},
{"learn":[0.3182519251],"iteration":484,"passed_time":0.1364218821,"remaining_time":0.144860349},
{"learn":[0.3179115918],"iteration":485,"passed_time":0.1366143872,"remaining_time":0.144485175},
{"learn":[0.3175631553],"iteration":486,"passed_time":0.1368658106,"remaining_time":0.1441728149},
{"learn":[0.3172255472],"iteration":487,"passed_time":0.1372114865,"remaining_time":0.1439595924},
{"learn":[0.3170071225],"iteration":488,"passed_time":0.1374989108,"remaining_time":0.1436849558},
{"learn":[0.3168062249],"iteration":489,"passed_time":0.1377724181,"remaining_time":0.1433957821},
{"learn":[0.3165923129],"iteration":490,"passed_time":0.1381208857,"remaining_time":0.1431843805},
{"learn":[0.3162122919],"iteration":491,"passed_time":0.1383571836,"remaining_time":0.1428566042},
{"learn":[0.3158850239],"iteration":492,"passed_time":0.1386038152,"remaining_time":0.1425398262},
{"learn":[0.3155164918],"iteration":493,"passed_time":0.1391624134,"remaining_time":0.1425428769},
{"learn":[0.3152577786],"iteration":494,"passed_time":0.1394148368,"remaining_time":0.1422312981},
{"learn":[0.3151484973],"iteration":495,"passed_time":0.1398048055,"remaining_time":0.1420597217},
{"learn":[0.3148966302],"iteration":496,"passed_time":0.1400124777,"remaining_time":0.1417027692},
{"learn":[0.3147495744],"iteration":497,"passed_time":0.1407281634,"remaining_time":0.1418585101},
{"learn":[0.3143013276],"iteration":498,"passed_time":0.1410327965,"remaining_time":0.1415980582},
{"learn":[0.3140640247],"iteration":499,"passed_time":0.1413839725,"remaining_time":0.1413839725},
{"learn":[0.3136879448],"iteration":500,"passed_time":0.1436091985,"remaining_time":0.1430359082},
{"learn":[0.3134123538],"iteration":501,"passed_time":0.1439156233,"remaining_time":0.1427688853},
{"learn":[0.3130728009],"iteration":502,"passed_time":0.1442358818,"remaining_time":0.1425153743},
{"learn":[0.3127450132],"iteration":503,"passed_time":0.1445508485,"remaining_time":0.1422563906},
{"learn":[0.3124387372],"iteration":504,"passed_time":0.144931067,"remaining_time":0.1420611449},
{"learn":[0.3119755979],"iteration":505,"passed_time":0.1452922849,"remaining_time":0.1418466181},
{"learn":[0.3117388799],"iteration":506,"passed_time":0.1455916262,"remaining_time":0.1415713446},
{"learn":[0.3114648682],"iteration":507,"passed_time":0.1459019678,"remaining_time":0.1413066303},
{"learn":[0.3111570781],"iteration":508,"passed_time":0.1461856837,"remaining_time":0.1410160525},
{"learn":[0.310860645],"iteration":509,"passed_time":0.1464807332,"remaining_time":0.1407363908},
{"learn":[0.3103917085],"iteration":510,"passed_time":0.1468398678,"remaining_time":0.1405179948},
{"learn":[0.3101161373],"iteration":511,"passed_time":0.1470874994,"remaining_time":0.1401927729},
{"learn":[0.3098271783],"iteration":512,"passed_time":0.1473760487,"remaining_time":0.1399066974},
{"learn":[0.3095151595],"iteration":513,"passed_time":0.1476486393,"remaining_time":0.1396055228},
{"learn":[0.3092345827],"iteration":514,"passed_time":0.1478419778,"remaining_time":0.1392298238},
{"learn":[0.3088635049],"iteration":515,"passed_time":0.1482210296,"remaining_time":0.1390290277},
{"learn":[0.3085747344],"iteration":516,"passed_time":0.1485138707,"remaining_time":0.1387470011},
{"learn":[0.3083759459],"iteration":517,"passed_time":0.1487956282,"remaining_time":0.1384546193},
{"learn":[0.3081830028],"iteration":518,"passed_time":0.1489929668,"remaining_time":0.1380840405},
{"learn":[0.3079957237],"iteration":519,"passed_time":0.1493048084,"remaining_time":0.1378198232},
{"learn":[0.3077963547],"iteration":520,"passed_time":0.1495598152,"remaining_time":0.1375031699},
{"learn":[0.307614864],"iteration":521,"passed_time":0.1498360309,"remaining_time":0.1372061739},
{"learn":[0.3073531706],"iteration":522,"passed_time":0.1501410807,"remaining_time":0.1369355554},
{"learn":[0.3071092654],"iteration":523,"passed_time":0.1503801287,"remaining_time":0.1366048498},
{"learn":[0.3069189034],"iteration":524,"passed_time":0.1508423077,"remaining_time":0.1364763736},
{"learn":[0.3066872845],"iteration":525,"passed_time":0.1510618135,"remaining_time":0.136127946},
{"learn":[0.3065025982],"iteration":526,"passed_time":0.1513090285,"remaining_time":0.1358048775},
{"learn":[0.306301469],"iteration":527,"passed_time":0.1515037836,"remaining_time":0.1354352005},
{"learn":[0.3061381337],"iteration":528,"passed_time":0.1517367065,"remaining_time":0.1351001678},
{"learn":[0.3057924751],"iteration":529,"passed_time":0.151982088,"remaining_time":0.1347765686},
{"learn":[0.305515185],"iteration":530,"passed_time":0.1522218028,"remaining_time":0.1344482589},
{"learn":[0.3052467258],"iteration":531,"passed_time":0.1524164329,"remaining_time":0.1340806215},
{"learn":[0.3049746371],"iteration":532,"passed_time":0.1526964821,"remaining_time":0.1337884749},
{"learn":[0.3046381054],"iteration":533,"passed_time":0.1529170296,"remaining_time":0.1334444491},
{"learn":[0.3042254152],"iteration":534,"passed_time":0.1531954954,"remaining_time":0.1331512249},
{"learn":[0.3039893309],"iteration":535,"passed_time":0.153384167,"remaining_time":0.1327803237},
{"learn":[0.3037497163],"iteration":536,"passed_time":0.1536545492,"remaining_time":0.1324805518},
{"learn":[0.3034624255],"iteration":537,"passed_time":0.1539090977,"remaining_time":0.1321672921},
{"learn":[0.3032484557],"iteration":538,"passed_time":0.1542164809,"remaining_time":0.1318994391},
{"learn":[0.3030134619],"iteration":539,"passed_time":0.1551505891,"remaining_time":0.1321653166},
{"learn":[0.3028405814],"iteration":540,"passed_time":0.1553924705,"remaining_time":0.1318394528},
{"learn":[0.3026651712],"iteration":541,"passed_time":0.1556656861,"remaining_time":0.1315403768},
{"learn":[0.3026047215],"iteration":542,"passed_time":0.1559015257,"remaining_time":0.1312099397},
{"learn":[0.3023778026],"iteration":543,"passed_time":0.1561409488,"remaining_time":0.1308828541},
{"learn":[0.3020889025],"iteration":544,"passed_time":0.1563832469,"remaining_time":0.1305584905},
{"learn":[0.3019302623],"iteration":545,"passed_time":0.1565725436,"remaining_time":0.1301903568},
{"learn":[0.3016787632],"iteration":546,"passed_time":0.1568255087,"remaining_time":0.1298756041},
{"learn":[0.3014141971],"iteration":547,"passed_time":0.157088599,"remaining_time":0.1295694284},
{"learn":[0.3011588002],"iteration":548,"passed_time":0.1573316471,"remaining_time":0.1292469451},
{"learn":[0.3008563717],"iteration":549,"passed_time":0.1575819038,"remaining_time":0.1289306486},
{"learn":[0.3006484256],"iteration":550,"passed_time":0.1578498693,"remaining_time":0.1286290223},
{"learn":[0.3004310967],"iteration":551,"passed_time":0.1581993786,"remaining_time":0.1283936986},
{"learn":[0.300235525],"iteration":552,"passed_time":0.1584794694,"remaining_time":0.1281018496},
{"learn":[0.2999579172],"iteration":553,"passed_time":0.1587304761,"remaining_time":0.1277866287},
{"learn":[0.2996564396],"iteration":554,"passed_time":0.1589190644,"remaining_time":0.1274215922},
{"learn":[0.2994110325],"iteration":555,"passed_time":0.1591496122,"remaining_time":0.1270906975},
{"learn":[0.2990093364],"iteration":556,"passed_time":0.1594169527,"remaining_time":0.1267894255},
{"learn":[0.2987466477],"iteration":557,"passed_time":0.1596746679,"remaining_time":0.1264806509},
{"learn":[0.298506385],"iteration":558,"passed_time":0.1598648396,"remaining_time":0.1261187733},
{"learn":[0.2983384569],"iteration":559,"passed_time":0.160056303,"remaining_time":0.1257585238},
{"learn":[0.2980948847],"iteration":560,"passed_time":0.1603040179,"remaining_time":0.1254428946},
{"learn":[0.2978974014],"iteration":561,"passed_time":0.1605375242,"remaining_time":0.1251164334},
{"learn":[0.2976612446],"iteration":562,"passed_time":0.1607273625,"remaining_time":0.1247564075},
{"learn":[0.2974038624],"iteration":563,"passed_time":0.1609369098,"remaining_time":0.124412221},
{"learn":[0.2971342834],"iteration":564,"passed_time":0.1611855831,"remaining_time":0.1240986348},
{"learn":[0.2967789013],"iteration":565,"passed_time":0.1613800049,"remaining_time":0.1237436787},
{"learn":[0.2965876063],"iteration":566,"passed_time":0.1616801796,"remaining_time":0.123470049},
{"learn":[0.2964010747],"iteration":567,"passed_time":0.1618797682,"remaining_time":0.1231198237},
{"learn":[0.2962550401],"iteration":568,"passed_time":0.1622375278,"remaining_time":0.1228899375},
{"learn":[0.2958581179],"iteration":569,"passed_time":0.1624680756,"remaining_time":0.1225636359},
{"learn":[0.295694954],"iteration":570,"passed_time":0.162660664,"remaining_time":0.1222091504},
{"learn":[0.2953846713],"iteration":571,"passed_time":0.1628640861,"remaining_time":0.1218633372},
{"learn":[0.2951147175],"iteration":572,"passed_time":0.1630551329,"remaining_time":0.1215087988},
{"learn":[0.2946965439],"iteration":573,"passed_time":0.1632885557,"remaining_time":0.12118628},
{"learn":[0.2944241858],"iteration":574,"passed_time":0.1635582296,"remaining_time":0.1208908653},
{"learn":[0.2941946104],"iteration":575,"passed_time":0.1638015277,"remaining_time":0.1205761246},
{"learn":[0.2940054938],"iteration":576,"passed_time":0.1640785768,"remaining_time":0.1202863743},
{"learn":[0.29385146],"iteration":577,"passed_time":0.1643406671,"remaining_time":0.1199857466},
{"learn":[0.2936027814],"iteration":578,"passed_time":0.1645686732,"remaining_time":0.1196604687},
{"learn":[0.2934290197],"iteration":579,"passed_time":0.1647708869,"remaining_time":0.1193168491},
{"learn":[0.2931913905],"iteration":580,"passed_time":0.1650161434,"remaining_time":0.1190047575},
{"learn":[0.2930208055],"iteration":581,"passed_time":0.1652622333,"remaining_time":0.118693494},
{"learn":[0.2928219369],"iteration":582,"passed_time":0.1656197011,"remaining_time":0.118462119},
{"learn":[0.292565205],"iteration":583,"passed_time":0.1658806248,"remaining_time":0.1181615409},
{"learn":[0.2923423326],"iteration":584,"passed_time":0.166116256,"remaining_time":0.117843156},
{"learn":[0.2921325481],"iteration":585,"passed_time":0.1663958051,"remaining_time":0.1175560808},
{"learn":[0.2919570264],"iteration":586,"passed_time":0.1666288947,"remaining_time":0.1172363433},
{"learn":[0.2918198953],"iteration":587,"passed_time":0.1668421504,"remaining_time":0.1169030033},
{"learn":[0.2915713835],"iteration":588,"passed_time":0.1671437,"remaining_time":0.116631682},
{"learn":[0.2913874533],"iteration":589,"passed_time":0.1674047903,"remaining_time":0.1163321424},
{"learn":[0.2911473432],"iteration":590,"passed_time":0.1677023816,"remaining_time":0.1160579933},
{"learn":[0.2909568945],"iteration":591,"passed_time":0.1679012202,"remaining_time":0.1157157058},
{"learn":[0.2907276589],"iteration":592,"passed_time":0.1681626022,"remaining_time":0.1154168281},
{"learn":[0.2905595385],"iteration":593,"passed_time":0.1684677353,"remaining_time":0.1151479807},
{"learn":[0.2903030067],"iteration":594,"passed_time":0.1686792826,"remaining_time":0.11481531},
{"learn":[0.2901488575],"iteration":595,"passed_time":0.1689499981,"remaining_time":0.1145231531},
{"learn":[0.2899914881],"iteration":596,"passed_time":0.1692014632,"remaining_time":0.1142180731},
{"learn":[0.2897909417],"iteration":597,"passed_time":0.1694353861,"remaining_time":0.1139013799},
{"learn":[0.2897053435],"iteration":598,"passed_time":0.1696932679,"remaining_time":0.1136010024},
{"learn":[0.2894351523],"iteration":599,"passed_time":0.1699721504,"remaining_time":0.1133147669},
{"learn":[0.2892115117],"iteration":600,"passed_time":0.170173239,"remaining_time":0.1129769091},
{"learn":[0.2890401785],"iteration":601,"passed_time":0.1704399545,"remaining_time":0.1126828935},
{"learn":[0.2889448897],"iteration":602,"passed_time":0.1706799192,"remaining_time":0.1123713564},
{"learn":[0.2888187334],"iteration":603,"passed_time":0.1709244674,"remaining_time":0.1120630614},
{"learn":[0.2886081348],"iteration":604,"passed_time":0.1711621404,"remaining_time":0.1117504883},
{"learn":[0.2884128726],"iteration":605,"passed_time":0.1715246917,"remaining_time":0.111519354},
{"learn":[0.2881625117],"iteration":606,"passed_time":0.1717802818,"remaining_time":0.111218535},
{"learn":[0.2879833986],"iteration":607,"passed_time":0.172012413,"remaining_time":0.11090274},
{"learn":[0.2878405486],"iteration":608,"passed_time":0.1722535861,"remaining_time":0.1105930249},
{"learn":[0.2875934219],"iteration":609,"passed_time":0.1724680085,"remaining_time":0.1102664316},
{"learn":[0.287361543],"iteration":610,"passed_time":0.1726941395,"remaining_time":0.10994766},
{"learn":[0.2872043025],"iteration":611,"passed_time":0.1729320625,"remaining_time":0.1096366671},
{"learn":[0.2870409551],"iteration":612,"passed_time":0.1733754493,"remaining_time":0.1094556262},
{"learn":[0.2868893268],"iteration":613,"passed_time":0.173727417,"remaining_time":0.1092162589},
{"learn":[0.2866510883],"iteration":614,"passed_time":0.1739208805,"remaining_time":0.1088772992},
{"learn":[0.2864685649],"iteration":615,"passed_time":0.1741354279,"remaining_time":0.108551955},
{"learn":[0.2862331889],"iteration":616,"passed_time":0.174354392,"remaining_time":0.1082297117},
{"learn":[0.2861095761],"iteration":617,"passed_time":0.1746555667,"remaining_time":0.1079586189},
{"learn":[0.2858948521],"iteration":618,"passed_time":0.1748733642,"remaining_time":0.1076361095},
{"learn":[0.2855307999],"iteration":619,"passed_time":0.1750742862,"remaining_time":0.1073035948},
{"learn":[0.285226728],"iteration":620,"passed_time":0.1753018339,"remaining_time":0.1069877537},
{"learn":[0.2849990232],"iteration":621,"passed_time":0.1755089228,"remaining_time":0.1066597634},
{"learn":[0.2847898771],"iteration":622,"passed_time":0.1757152616,"remaining_time":0.1063317073},
{"learn":[0.2843719449],"iteration":623,"passed_time":0.1760513539,"remaining_time":0.106082226},
{"learn":[0.2841598302],"iteration":624,"passed_time":0.1762348171,"remaining_time":0.1057408903},
{"learn":[0.2839520808],"iteration":625,"passed_time":0.176420197,"remaining_time":0.105401204},
{"learn":[0.283833195],"iteration":626,"passed_time":0.1766379945,"remaining_time":0.105081295},
{"learn":[0.2835776517],"iteration":627,"passed_time":0.1769246271,"remaining_time":0.1048024861},
{"learn":[0.2834565619],"iteration":628,"passed_time":0.1772005511,"remaining_time":0.1045173362},
{"learn":[0.2833313285],"iteration":629,"passed_time":0.1774326823,"remaining_time":0.104206496},
{"learn":[0.2831564622],"iteration":630,"passed_time":0.1776886475,"remaining_time":0.103909843},
{"learn":[0.2830498756],"iteration":631,"passed_time":0.1779682382,"remaining_time":0.1036270754},
{"learn":[0.2829000666],"iteration":632,"passed_time":0.1781560349,"remaining_time":0.1032910976},
{"learn":[0.2826412934],"iteration":633,"passed_time":0.1783900828,"remaining_time":0.1029822875},
{"learn":[0.2824937968],"iteration":634,"passed_time":0.1786454229,"remaining_time":0.1026859518},
{"learn":[0.2822391168],"iteration":635,"passed_time":0.1789253887,"remaining_time":0.1024038388},
{"learn":[0.2820068524],"iteration":636,"passed_time":0.1791648951,"remaining_time":0.1020986765},
{"learn":[0.2817816217],"iteration":637,"passed_time":0.1794596113,"remaining_time":0.1018250459},
{"learn":[0.2815367921],"iteration":638,"passed_time":0.1797356603,"remaining_time":0.1015408034},
{"learn":[0.2813917123],"iteration":639,"passed_time":0.1800317098,"remaining_time":0.1012678368},
{"learn":[0.2811414213],"iteration":640,"passed_time":0.1802277984,"remaining_time":0.1009388138},
{"learn":[0.2810910477],"iteration":641,"passed_time":0.1805178478,"remaining_time":0.1006626005},
{"learn":[0.2807238377],"iteration":642,"passed_time":0.1808633987,"remaining_time":0.1004171591},
{"learn":[0.2805347746],"iteration":643,"passed_time":0.1811996159,"remaining_time":0.1001662473},
{"learn":[0.280346768],"iteration":644,"passed_time":0.1815152493,"remaining_time":0.09990374189},
{"learn":[0.2801023589],"iteration":645,"passed_time":0.1817164214,"remaining_time":0.09957834855},
{"learn":[0.2798642735],"iteration":646,"passed_time":0.1819110932,"remaining_time":0.09924979274},
{"learn":[0.279745942],"iteration":647,"passed_time":0.1821010566,"remaining_time":0.09891909248},
{"learn":[0.2795517149],"iteration":648,"passed_time":0.1823348128,"remaining_time":0.09861251048},
{"learn":[0.2793495657],"iteration":649,"passed_time":0.1826094868,"remaining_time":0.0983281852},
{"learn":[0.2791837653],"iteration":650,"passed_time":0.1829530376,"remaining_time":0.09808081433},
{"learn":[0.2790125633],"iteration":651,"passed_time":0.1831675433,"remaining_time":0.09776427159},
{"learn":[0.2788184336],"iteration":652,"passed_time":0.1834784266,"remaining_time":0.09749925579},
{"learn":[0.2787364475],"iteration":653,"passed_time":0.1836845571,"remaining_time":0.09717868005},
{"learn":[0.2786792409],"iteration":654,"passed_time":0.1839037713,"remaining_time":0.09686534517},
{"learn":[0.2785432416],"iteration":655,"passed_time":0.1841726534,"remaining_time":0.09657834265},
{"learn":[0.2783550063],"iteration":656,"passed_time":0.1843544499,"remaining_time":0.09624593048},
{"learn":[0.2781931645],"iteration":657,"passed_time":0.1845512885,"remaining_time":0.09592179433},
{"learn":[0.2778065159],"iteration":658,"passed_time":0.1847440853,"remaining_time":0.09559595309},
{"learn":[0.2776117641],"iteration":659,"passed_time":0.1849644662,"remaining_time":0.095284725},
{"learn":[0.277384176],"iteration":660,"passed_time":0.1851985141,"remaining_time":0.09498078104},
{"learn":[0.277152783],"iteration":661,"passed_time":0.1854378121,"remaining_time":0.09467972884},
{"learn":[0.2770643471],"iteration":662,"passed_time":0.1856779435,"remaining_time":0.09437928652},
{"learn":[0.2769367517],"iteration":663,"passed_time":0.1858573649,"remaining_time":0.09404830515},
{"learn":[0.2767300248],"iteration":664,"passed_time":0.1860651205,"remaining_time":0.09373205317},
{"learn":[0.2765068922],"iteration":665,"passed_time":0.1862453336,"remaining_time":0.09340231445},
{"learn":[0.2763505878],"iteration":666,"passed_time":0.1864429222,"remaining_time":0.09308169879},
{"learn":[0.2762374521],"iteration":667,"passed_time":0.1866388024,"remaining_time":0.0927606024},
{"learn":[0.2760597309],"iteration":668,"passed_time":0.1868382661,"remaining_time":0.09244165331},
{"learn":[0.2758477694],"iteration":669,"passed_time":0.1870287295,"remaining_time":0.09211862795},
{"learn":[0.2755657557],"iteration":670,"passed_time":0.1872781944,"remaining_time":0.09182492693},
{"learn":[0.2752902444],"iteration":671,"passed_time":0.1875046171,"remaining_time":0.09152011074},
{"learn":[0.2751131697],"iteration":672,"passed_time":0.1877338316,"remaining_time":0.09121688399},
{"learn":[0.2750021715],"iteration":673,"passed_time":0.1879283368,"remaining_time":0.0908970887},
{"learn":[0.2748491768],"iteration":674,"passed_time":0.1881677598,"remaining_time":0.09059929175},
{"learn":[0.2746978757],"iteration":675,"passed_time":0.1884061411,"remaining_time":0.09030116824},
{"learn":[0.2745280846],"iteration":676,"passed_time":0.1885927294,"remaining_time":0.0899785105},
{"learn":[0.2743461509],"iteration":677,"passed_time":0.1889464889,"remaining_time":0.0897356481},
{"learn":[0.2741402179],"iteration":678,"passed_time":0.1892429134,"remaining_time":0.08946535377},
{"learn":[0.2740731038],"iteration":679,"passed_time":0.189501837,"remaining_time":0.08917733505},
{"learn":[0.2739097321],"iteration":680,"passed_time":0.1897300931,"remaining_time":0.08887503625},
{"learn":[0.2737212008],"iteration":681,"passed_time":0.1900396846,"remaining_time":0.08861087934},
{"learn":[0.2735516659],"iteration":682,"passed_time":0.1902481485,"remaining_time":0.08829965312},
{"learn":[0.2733423532],"iteration":683,"passed_time":0.1904855298,"remaining_time":0.08800208688},
{"learn":[0.2731670871],"iteration":684,"passed_time":0.1907164943,"remaining_time":0.08770174556},
{"learn":[0.2729634695],"iteration":685,"passed_time":0.1910154189,"remaining_time":0.08743271363},
{"learn":[0.2728415302],"iteration":686,"passed_time":0.1912716758,"remaining_time":0.08714415504},
{"learn":[0.2727038473],"iteration":687,"passed_time":0.1914793896,"remaining_time":0.08683367669},
{"learn":[0.2725653255],"iteration":688,"passed_time":0.1917166043,"remaining_time":0.08653681267},
{"learn":[0.2724208941],"iteration":689,"passed_time":0.191957444,"remaining_time":0.08624175021},
{"learn":[0.2721980937],"iteration":690,"passed_time":0.1922421183,"remaining_time":0.08596644652},
{"learn":[0.2720426804],"iteration":691,"passed_time":0.1925217507,"remaining_time":0.0856888717},
{"learn":[0.2719130001],"iteration":692,"passed_time":0.1927512152,"remaining_time":0.08538906645},
{"learn":[0.271773288],"iteration":693,"passed_time":0.19305739,"remaining_time":0.08512328722},
{"learn":[0.2714838677],"iteration":694,"passed_time":0.1933229804,"remaining_time":0.08483958132},
{"learn":[0.2713097993],"iteration":695,"passed_time":0.1935780705,"remaining_time":0.08455134114},
{"learn":[0.2711141484],"iteration":696,"passed_time":0.1939235797,"remaining_time":0.08430250308},
{"learn":[0.2708369293],"iteration":697,"passed_time":0.1941914202,"remaining_time":0.08401978351},
{"learn":[0.2705633455],"iteration":698,"passed_time":0.1943947172,"remaining_time":0.08370931315},
{"learn":[0.2704281707],"iteration":699,"passed_time":0.1946126814,"remaining_time":0.08340543488},
{"learn":[0.2702345871],"iteration":700,"passed_time":0.1948811885,"remaining_time":0.08312336001},
{"learn":[0.2701177207],"iteration":701,"passed_time":0.1951309452,"remaining_time":0.08283336419},
{"learn":[0.2698653388],"iteration":702,"passed_time":0.195375535,"remaining_time":0.0825413},
{"learn":[0.2696795737],"iteration":703,"passed_time":0.1956339169,"remaining_time":0.08225516961},
{"learn":[0.26951458],"iteration":704,"passed_time":0.1958673398,"remaining_time":0.08195867409},
{"learn":[0.2692777711],"iteration":705,"passed_time":0.1962831425,"remaining_time":0.08173830581},
{"learn":[0.2690930694],"iteration":706,"passed_time":0.1965649,"remaining_time":0.08146183268},
{"learn":[0.2688911774],"iteration":707,"passed_time":0.1967936561,"remaining_time":0.08116348529},
{"learn":[0.2685968097],"iteration":708,"passed_time":0.1970352875,"remaining_time":0.08087061873},
{"learn":[0.2684086971],"iteration":709,"passed_time":0.1972819608,"remaining_time":0.08057995581},
{"learn":[0.2681457893],"iteration":710,"passed_time":0.1975225505,"remaining_time":0.08028694388},
{"learn":[0.2680947761],"iteration":711,"passed_time":0.1979711041,"remaining_time":0.08007819942},
{"learn":[0.2679887631],"iteration":712,"passed_time":0.1982061104,"remaining_time":0.07978282424},
{"learn":[0.2676493714],"iteration":713,"passed_time":0.1984864512,"remaining_time":0.07950577736},
{"learn":[0.2675068918],"iteration":714,"passed_time":0.1986837898,"remaining_time":0.07919563648},
{"learn":[0.2672670006],"iteration":715,"passed_time":0.1990505495,"remaining_time":0.07895301127},
{"learn":[0.2669756522],"iteration":716,"passed_time":0.1992860141,"remaining_time":0.07865821757},
{"learn":[0.266862971],"iteration":717,"passed_time":0.1996372318,"remaining_time":0.07840905205},
{"learn":[0.2667150615],"iteration":718,"passed_time":0.1998846134,"remaining_time":0.07811902137},
{"learn":[0.2665707278],"iteration":719,"passed_time":0.2001307866,"remaining_time":0.07782863924},
{"learn":[0.2663945971],"iteration":720,"passed_time":0.2003069163,"remaining_time":0.07751127552},
{"learn":[0.2662544654],"iteration":721,"passed_time":0.2005501728,"remaining_time":0.07722014964},
{"learn":[0.2660050157],"iteration":722,"passed_time":0.201435613,"remaining_time":0.07717519338},
{"learn":[0.2659632429],"iteration":723,"passed_time":0.2016373684,"remaining_time":0.07686728409},
{"learn":[0.2657182843],"iteration":724,"passed_time":0.201885625,"remaining_time":0.07657730604},
{"learn":[0.2656046017],"iteration":725,"passed_time":0.2021305482,"remaining_time":0.07628618486},
{"learn":[0.2654167148],"iteration":726,"passed_time":0.2023523874,"remaining_time":0.07598652238},
{"learn":[0.2652913057],"iteration":727,"passed_time":0.2025784351,"remaining_time":0.07568864609},
{"learn":[0.2652033919],"iteration":728,"passed_time":0.2027824822,"remaining_time":0.07538278832},
{"learn":[0.265016389],"iteration":729,"passed_time":0.2030677398,"remaining_time":0.07510724624},
{"learn":[0.2648784973],"iteration":730,"passed_time":0.2033649977,"remaining_time":0.07483609356},
{"learn":[0.2646594289],"iteration":731,"passed_time":0.203714632,"remaining_time":0.07458404561},
{"learn":[0.2645903365],"iteration":732,"passed_time":0.20395093,"remaining_time":0.0742904479},
{"learn":[0.264364322],"iteration":733,"passed_time":0.2041393934,"remaining_time":0.07397967116},
{"learn":[0.2642514768],"iteration":734,"passed_time":0.2043515657,"remaining_time":0.07367777538},
{"learn":[0.2642023509],"iteration":735,"passed_time":0.2046189061,"remaining_time":0.07339591198},
{"learn":[0.2640939456],"iteration":736,"passed_time":0.2048203282,"remaining_time":0.07309056486},
{"learn":[0.2640565244],"iteration":737,"passed_time":0.2050431257,"remaining_time":0.072793088},
{"learn":[0.2637887635],"iteration":738,"passed_time":0.2052755069,"remaining_time":0.07249919798},
{"learn":[0.2636440426],"iteration":739,"passed_time":0.2055311804,"remaining_time":0.07221365798},
{"learn":[0.2635870572],"iteration":740,"passed_time":0.2057374359,"remaining_time":0.07191092564},
{"learn":[0.263509204],"iteration":741,"passed_time":0.2059827758,"remaining_time":0.07162204333},
{"learn":[0.2634320809],"iteration":742,"passed_time":0.2062361158,"remaining_time":0.07133604545},
{"learn":[0.2633185415],"iteration":743,"passed_time":0.206467247,"remaining_time":0.07104249359},
{"learn":[0.2631448519],"iteration":744,"passed_time":0.2066536686,"remaining_time":0.07073380604},
{"learn":[0.2629913599],"iteration":745,"passed_time":0.206966552,"remaining_time":0.07046850429},
{"learn":[0.2629777879],"iteration":746,"passed_time":0.2072110168,"remaining_time":0.07017990261},
{"learn":[0.2627931586],"iteration":747,"passed_time":0.2074025636,"remaining_time":0.06987359093},
{"learn":[0.2626797287],"iteration":748,"passed_time":0.2076511952,"remaining_time":0.06958671561},
{"learn":[0.2625876322],"iteration":749,"passed_time":0.2079627035,"remaining_time":0.06932090116},
{"learn":[0.2625822052],"iteration":750,"passed_time":0.2082267522,"remaining_time":0.06903922942},
{"learn":[0.2624301491],"iteration":751,"passed_time":0.2084369661,"remaining_time":0.06873985052},
{"learn":[0.262334328],"iteration":752,"passed_time":0.2086953063,"remaining_time":0.0684564949},
{"learn":[0.262180454],"iteration":753,"passed_time":0.2088893532,"remaining_time":0.06815222928},
{"learn":[0.2619260443],"iteration":754,"passed_time":0.2091246928,"remaining_time":0.06786165526},
{"learn":[0.2617978664],"iteration":755,"passed_time":0.2094117004,"remaining_time":0.0675879033},
{"learn":[0.261602667],"iteration":756,"passed_time":0.2097218336,"remaining_time":0.06732153973},
{"learn":[0.2615534248],"iteration":757,"passed_time":0.2099156721,"remaining_time":0.06701793227},
{"learn":[0.2613847161],"iteration":758,"passed_time":0.2101661371,"remaining_time":0.06673259427},
{"learn":[0.2612113077],"iteration":759,"passed_time":0.2104040185,"remaining_time":0.06644337426},
{"learn":[0.2610424365],"iteration":760,"passed_time":0.2105907734,"remaining_time":0.0661382324},
{"learn":[0.2607917259],"iteration":761,"passed_time":0.2109376577,"remaining_time":0.06588341539},
{"learn":[0.2605512782],"iteration":762,"passed_time":0.2112977089,"remaining_time":0.06563244694},
{"learn":[0.2603085341],"iteration":763,"passed_time":0.2116905944,"remaining_time":0.06539133544},
{"learn":[0.2601438998],"iteration":764,"passed_time":0.2119906857,"remaining_time":0.06512132176},
{"learn":[0.2599965004],"iteration":765,"passed_time":0.2122209419,"remaining_time":0.06482989607},
{"learn":[0.2599021939],"iteration":766,"passed_time":0.2130105462,"remaining_time":0.06470854924},
{"learn":[0.2598473933],"iteration":767,"passed_time":0.2139567381,"remaining_time":0.06463276462},
{"learn":[0.2598127266],"iteration":768,"passed_time":0.2141488265,"remaining_time":0.06432819106},
{"learn":[0.2595890459],"iteration":769,"passed_time":0.2144256672,"remaining_time":0.06404922527},
{"learn":[0.2595124434],"iteration":770,"passed_time":0.2146302977,"remaining_time":0.06374881734},
{"learn":[0.2595064329],"iteration":771,"passed_time":0.2148386782,"remaining_time":0.06344976507},
{"learn":[0.2593226699],"iteration":772,"passed_time":0.2150983101,"remaining_time":0.06316599793},
{"learn":[0.2592284332],"iteration":773,"passed_time":0.2153482751,"remaining_time":0.06287947051},
{"learn":[0.2591844711],"iteration":774,"passed_time":0.215556864,"remaining_time":0.06258102503},
{"learn":[0.2590989723],"iteration":775,"passed_time":0.2157992871,"remaining_time":0.06229257773},
{"learn":[0.2588811745],"iteration":776,"passed_time":0.2160865864,"remaining_time":0.06201712841},
{"learn":[0.2588697842],"iteration":777,"passed_time":0.2163355514,"remaining_time":0.06173071004},
{"learn":[0.2586937612],"iteration":778,"passed_time":0.2165668492,"remaining_time":0.06143937571},
{"learn":[0.2585822495],"iteration":779,"passed_time":0.2167697296,"remaining_time":0.06114018015},
{"learn":[0.2583577107],"iteration":780,"passed_time":0.2169647765,"remaining_time":0.06083903464},
{"learn":[0.2583162143],"iteration":781,"passed_time":0.2171856157,"remaining_time":0.06054535067},
{"learn":[0.2583095387],"iteration":782,"passed_time":0.2174119967,"remaining_time":0.06025338862},
{"learn":[0.2582469832],"iteration":783,"passed_time":0.217622419,"remaining_time":0.05995719707},
{"learn":[0.2582003729],"iteration":784,"passed_time":0.2178511751,"remaining_time":0.05966624541},
{"learn":[0.2580682317],"iteration":785,"passed_time":0.2180515554,"remaining_time":0.05936772628},
{"learn":[0.2579044429],"iteration":786,"passed_time":0.2183578552,"remaining_time":0.05909812346},
{"learn":[0.2578278512],"iteration":787,"passed_time":0.218636946,"remaining_time":0.0588211073},
{"learn":[0.2577331541],"iteration":788,"passed_time":0.2188160341,"remaining_time":0.05851734245},
{"learn":[0.2576854435],"iteration":789,"passed_time":0.2190232063,"remaining_time":0.05822135863},
{"learn":[0.257458243],"iteration":790,"passed_time":0.2192703795,"remaining_time":0.05793616855},
{"learn":[0.2574417937],"iteration":791,"passed_time":0.2195138444,"remaining_time":0.05765010054},
{"learn":[0.25723327],"iteration":792,"passed_time":0.2197739763,"remaining_time":0.05736849065},
{"learn":[0.25718094],"iteration":793,"passed_time":0.2200188578,"remaining_time":0.05708297822},
{"learn":[0.2570138742],"iteration":794,"passed_time":0.220201946,"remaining_time":0.05678163388},
{"learn":[0.2570002218],"iteration":795,"passed_time":0.2203846175,"remaining_time":0.05648047987},
{"learn":[0.2568369908],"iteration":796,"passed_time":0.2206382076,"remaining_time":0.05619768651},
{"learn":[0.2566533373],"iteration":797,"passed_time":0.2209002979,"remaining_time":0.05591711802},
{"learn":[0.2564803052],"iteration":798,"passed_time":0.2210914697,"remaining_time":0.0556187552},
{"learn":[0.256392291],"iteration":799,"passed_time":0.2213024336,"remaining_time":0.05532560841},
{"learn":[0.2560625685],"iteration":800,"passed_time":0.2222632092,"remaining_time":0.05521894961},
{"learn":[0.2558865188],"iteration":801,"passed_time":0.2225578837,"remaining_time":0.05494571194},
{"learn":[0.2557264176],"iteration":802,"passed_time":0.2227607641,"remaining_time":0.05464990104},
{"learn":[0.2557214823],"iteration":803,"passed_time":0.2230598554,"remaining_time":0.0543777757},
{"learn":[0.2556759731],"iteration":804,"passed_time":0.2233819057,"remaining_time":0.05411114485},
{"learn":[0.2556089241],"iteration":805,"passed_time":0.2236489128,"remaining_time":0.05383112789},
{"learn":[0.255604004],"iteration":806,"passed_time":0.2238635018,"remaining_time":0.053538607},
{"learn":[0.2555075862],"iteration":807,"passed_time":0.2240684239,"remaining_time":0.05324398193},
{"learn":[0.2553492696],"iteration":808,"passed_time":0.224306597,"remaining_time":0.05295742895},
{"learn":[0.2552649547],"iteration":809,"passed_time":0.2245798542,"remaining_time":0.05267922507},
{"learn":[0.2551628812],"iteration":810,"passed_time":0.2247831096,"remaining_time":0.05238471976},
{"learn":[0.255127056],"iteration":811,"passed_time":0.2250029905,"remaining_time":0.05209428844},
{"learn":[0.2549438659],"iteration":812,"passed_time":0.2251922039,"remaining_time":0.05179697678},
{"learn":[0.254812362],"iteration":813,"passed_time":0.2254036678,"remaining_time":0.05150501501},
{"learn":[0.2547716419],"iteration":814,"passed_time":0.2256973423,"remaining_time":0.05123191206},
{"learn":[0.254563128],"iteration":815,"passed_time":0.2259740163,"remaining_time":0.05095492525},
{"learn":[0.2544009385],"iteration":816,"passed_time":0.2262527321,"remaining_time":0.05067839654},
{"learn":[0.2543962221],"iteration":817,"passed_time":0.2265425315,"remaining_time":0.05040432852},
{"learn":[0.2543252925],"iteration":818,"passed_time":0.2268393727,"remaining_time":0.05013177834},
{"learn":[0.2541626532],"iteration":819,"passed_time":0.2271274637,"remaining_time":0.04985724813},
{"learn":[0.254158453],"iteration":820,"passed_time":0.2274575975,"remaining_time":0.04959185135},
{"learn":[0.2540448059],"iteration":821,"passed_time":0.2277741476,"remaining_time":0.04932335556},
{"learn":[0.2539227107],"iteration":822,"passed_time":0.2280608636,"remaining_time":0.04904832667},
{"learn":[0.2537557328],"iteration":823,"passed_time":0.2282554104,"remaining_time":0.04875358281},
{"learn":[0.2537480363],"iteration":824,"passed_time":0.2284732079,"remaining_time":0.04846401379},
{"learn":[0.2537453078],"iteration":825,"passed_time":0.228651671,"remaining_time":0.04816633263},
{"learn":[0.253629078],"iteration":826,"passed_time":0.228954679,"remaining_time":0.04789499332},
{"learn":[0.2534974592],"iteration":827,"passed_time":0.2291722682,"remaining_time":0.04760583348},
{"learn":[0.2533690266],"iteration":828,"passed_time":0.2294286917,"remaining_time":0.04732485678},
{"learn":[0.2532155422],"iteration":829,"passed_time":0.2296845318,"remaining_time":0.04704381977},
{"learn":[0.2531599259],"iteration":830,"passed_time":0.2299641226,"remaining_time":0.04676767355},
{"learn":[0.2531554828],"iteration":831,"passed_time":0.2302680057,"remaining_time":0.04649642422},
{"learn":[0.2530030325],"iteration":832,"passed_time":0.2305702221,"remaining_time":0.0462247624},
{"learn":[0.2529750906],"iteration":833,"passed_time":0.230845271,"remaining_time":0.0459476199},
{"learn":[0.2529663352],"iteration":834,"passed_time":0.2311589044,"remaining_time":0.04567810686},
{"learn":[0.2528462391],"iteration":835,"passed_time":0.2315000801,"remaining_time":0.04541389132},
{"learn":[0.2526532542],"iteration":836,"passed_time":0.2317002521,"remaining_time":0.04512203238},
{"learn":[0.2525787228],"iteration":837,"passed_time":0.2318915489,"remaining_time":0.04482867652},
{"learn":[0.2524214154],"iteration":838,"passed_time":0.2322013905,"remaining_time":0.04455831212},
{"learn":[0.2523565854],"iteration":839,"passed_time":0.2324135628,"remaining_time":0.04426925006},
{"learn":[0.2521795139],"iteration":840,"passed_time":0.2327517801,"remaining_time":0.044004201},
{"learn":[0.2520395313],"iteration":841,"passed_time":0.2330211206,"remaining_time":0.04372605352},
{"learn":[0.251917936],"iteration":842,"passed_time":0.2332193759,"remaining_time":0.04343468804},
{"learn":[0.2518344445],"iteration":843,"passed_time":0.2334694242,"remaining_time":0.04315311633},
{"learn":[0.2517572358],"iteration":844,"passed_time":0.2336718463,"remaining_time":0.04286288305},
{"learn":[0.2515685028],"iteration":845,"passed_time":0.2338655181,"remaining_time":0.04257126453},
{"learn":[0.251437455],"iteration":846,"passed_time":0.2341497757,"remaining_time":0.04229624047},
{"learn":[0.2512833893],"iteration":847,"passed_time":0.2343548228,"remaining_time":0.04200699654},
{"learn":[0.2512018065],"iteration":848,"passed_time":0.2346529974,"remaining_time":0.04173451426},
{"learn":[0.2510834293],"iteration":849,"passed_time":0.2348860036,"remaining_time":0.04145047123},
{"learn":[0.2510141269],"iteration":850,"passed_time":0.2351331352,"remaining_time":0.04116902132},
{"learn":[0.2509033128],"iteration":851,"passed_time":0.2355265623,"remaining_time":0.04091306482},
{"learn":[0.250754525],"iteration":852,"passed_time":0.2357198175,"remaining_time":0.04062228977},
{"learn":[0.2505602794],"iteration":853,"passed_time":0.2359456152,"remaining_time":0.04033730657},
{"learn":[0.250330082],"iteration":854,"passed_time":0.2361958302,"remaining_time":0.04005660278},
{"learn":[0.2502082976],"iteration":855,"passed_time":0.2365673401,"remaining_time":0.03979637496},
{"learn":[0.2502044135],"iteration":856,"passed_time":0.2368409307,"remaining_time":0.03951954852},
{"learn":[0.2501106702],"iteration":857,"passed_time":0.2370940624,"remaining_time":0.03923934366},
{"learn":[0.2499420665],"iteration":858,"passed_time":0.2373164433,"remaining_time":0.03895415426},
{"learn":[0.2498403009],"iteration":859,"passed_time":0.2375570331,"remaining_time":0.03867207515},
{"learn":[0.249760561],"iteration":860,"passed_time":0.2377994145,"remaining_time":0.03839038167},
{"learn":[0.2496579979],"iteration":861,"passed_time":0.2380355041,"remaining_time":0.03810777212},
{"learn":[0.2496369472],"iteration":862,"passed_time":0.2382841774,"remaining_time":0.03782726803},
{"learn":[0.2496347087],"iteration":863,"passed_time":0.2384765575,"remaining_time":0.03753797665},
{"learn":[0.2495954129],"iteration":864,"passed_time":0.238705022,"remaining_time":0.037254541},
{"learn":[0.249438271],"iteration":865,"passed_time":0.2389601121,"remaining_time":0.03697535222},
{"learn":[0.2494345711],"iteration":866,"passed_time":0.2392595367,"remaining_time":0.03670302005},
{"learn":[0.2493568918],"iteration":867,"passed_time":0.2394709174,"remaining_time":0.03641723628},
{"learn":[0.2492051004],"iteration":868,"passed_time":0.239783884,"remaining_time":0.03614693764},
{"learn":[0.2490653326],"iteration":869,"passed_time":0.2400736834,"remaining_time":0.03587307913},
{"learn":[0.2490033786],"iteration":870,"passed_time":0.2402750638,"remaining_time":0.03558608866},
{"learn":[0.2489337037],"iteration":871,"passed_time":0.2404961113,"remaining_time":0.03530218148},
{"learn":[0.2488736985],"iteration":872,"passed_time":0.2406784078,"remaining_time":0.03501278098},
{"learn":[0.2487316708],"iteration":873,"passed_time":0.2411707959,"remaining_time":0.03476832985},
{"learn":[0.2485331767],"iteration":874,"passed_time":0.2413960936,"remaining_time":0.03448515623},
{"learn":[0.2483527992],"iteration":875,"passed_time":0.2417334776,"remaining_time":0.03421798085},
{"learn":[0.2483302118],"iteration":876,"passed_time":0.2419439832,"remaining_time":0.03393285055},
{"learn":[0.2482507471],"iteration":877,"passed_time":0.2422161154,"remaining_time":0.0336564534},
{"learn":[0.2481526006],"iteration":878,"passed_time":0.2425660414,"remaining_time":0.03339077476},
{"learn":[0.2479737239],"iteration":879,"passed_time":0.2427950475,"remaining_time":0.03310841557},
{"learn":[0.2477911413],"iteration":880,"passed_time":0.2431626823,"remaining_time":0.03284490261},
{"learn":[0.2476284688],"iteration":881,"passed_time":0.2433849799,"remaining_time":0.03256170933},
{"learn":[0.2474847155],"iteration":882,"passed_time":0.243678196,"remaining_time":0.03228805089},
{"learn":[0.2473681799],"iteration":883,"passed_time":0.2438964518,"remaining_time":0.03200451178},
{"learn":[0.2472005472],"iteration":884,"passed_time":0.2440997489,"remaining_time":0.03171917641},
{"learn":[0.247142806],"iteration":885,"passed_time":0.2443495056,"remaining_time":0.0314400041},
{"learn":[0.2469629601],"iteration":886,"passed_time":0.2445712198,"remaining_time":0.03115732564},
{"learn":[0.2468809786],"iteration":887,"passed_time":0.2448191431,"remaining_time":0.03087809012},
{"learn":[0.2468650459],"iteration":888,"passed_time":0.2450183151,"remaining_time":0.03059283799},
{"learn":[0.2467545],"iteration":889,"passed_time":0.245243571,"remaining_time":0.03031100316},
{"learn":[0.2467041586],"iteration":890,"passed_time":0.245441368,"remaining_time":0.03002593615},
{"learn":[0.2465055314],"iteration":891,"passed_time":0.2457377092,"remaining_time":0.02975299618},
{"learn":[0.2464259366],"iteration":892,"passed_time":0.2459778406,"remaining_time":0.02947326869},
{"learn":[0.2463237707],"iteration":893,"passed_time":0.2461654706,"remaining_time":0.02918740479},
{"learn":[0.2461397982],"iteration":894,"passed_time":0.246368226,"remaining_time":0.02890353489},
{"learn":[0.2459896776],"iteration":895,"passed_time":0.24657994,"remaining_time":0.02862088589},
{"learn":[0.2458222485],"iteration":896,"passed_time":0.2467649866,"remaining_time":0.0283353329},
{"learn":[0.2456870484],"iteration":897,"passed_time":0.2469838257,"remaining_time":0.02805384212},
{"learn":[0.2455242476],"iteration":898,"passed_time":0.247170789,"remaining_time":0.02776890956},
{"learn":[0.2454443358],"iteration":899,"passed_time":0.2474920059,"remaining_time":0.02749911177},
{"learn":[0.2452685718],"iteration":900,"passed_time":0.2478443486,"remaining_time":0.02723261988},
{"learn":[0.2450639123],"iteration":901,"passed_time":0.2480280618,"remaining_time":0.02694761648},
{"learn":[0.245061665],"iteration":902,"passed_time":0.2482779018,"remaining_time":0.02666994073},
{"learn":[0.2449775026],"iteration":903,"passed_time":0.2484641151,"remaining_time":0.02638556975},
{"learn":[0.2448421333],"iteration":904,"passed_time":0.2487289972,"remaining_time":0.02610967374},
{"learn":[0.2447930038],"iteration":905,"passed_time":0.2488596257,"remaining_time":0.02581987286},
{"learn":[0.2447428447],"iteration":906,"passed_time":0.2490577143,"remaining_time":0.02553734005},
{"learn":[0.2445740948],"iteration":907,"passed_time":0.2492534695,"remaining_time":0.02525475682},
{"learn":[0.2444221936],"iteration":908,"passed_time":0.2494897258,"remaining_time":0.02497641919},
{"learn":[0.2442627933],"iteration":909,"passed_time":0.2497138984,"remaining_time":0.02469697896},
{"learn":[0.2441957272],"iteration":910,"passed_time":0.249949613,"remaining_time":0.02441878766},
{"learn":[0.2440658588],"iteration":911,"passed_time":0.2501839942,"remaining_time":0.02414056085},
{"learn":[0.244012549],"iteration":912,"passed_time":0.2504181255,"remaining_time":0.02386240626},
{"learn":[0.2438306476],"iteration":913,"passed_time":0.2506738406,"remaining_time":0.02358637888},
{"learn":[0.2437631931],"iteration":914,"passed_time":0.2508763043,"remaining_time":0.02330544904},
{"learn":[0.2436257913],"iteration":915,"passed_time":0.2512257303,"remaining_time":0.02303816741},
{"learn":[0.2436227641],"iteration":916,"passed_time":0.2514296524,"remaining_time":0.0227575367},
{"learn":[0.2435508276],"iteration":917,"passed_time":0.2516738256,"remaining_time":0.02248066852},
{"learn":[0.2434175112],"iteration":918,"passed_time":0.251916207,"remaining_time":0.02220371357},
{"learn":[0.2432337455],"iteration":919,"passed_time":0.252128421,"remaining_time":0.02192421052},
{"learn":[0.2431115561],"iteration":920,"passed_time":0.252390053,"remaining_time":0.02164909249},
{"learn":[0.2429788596],"iteration":921,"passed_time":0.2525820998,"remaining_time":0.0213681169},
{"learn":[0.2428198678],"iteration":922,"passed_time":0.2528365649,"remaining_time":0.02109254116},
{"learn":[0.242696709],"iteration":923,"passed_time":0.2530469455,"remaining_time":0.02081338513},
{"learn":[0.2426679178],"iteration":924,"passed_time":0.253143198,"remaining_time":0.02052512417},
{"learn":[0.2425919378],"iteration":925,"passed_time":0.2533424117,"remaining_time":0.0202455059},
{"learn":[0.2425472768],"iteration":926,"passed_time":0.2535743762,"remaining_time":0.0199686402},
{"learn":[0.2425432164],"iteration":927,"passed_time":0.2538563837,"remaining_time":0.01969575391},
{"learn":[0.2423764905],"iteration":928,"passed_time":0.2541385995,"remaining_time":0.0194228639},
{"learn":[0.2423361941],"iteration":929,"passed_time":0.2543349798,"remaining_time":0.0191434931},
{"learn":[0.242235826],"iteration":930,"passed_time":0.2545314433,"remaining_time":0.01886430676},
{"learn":[0.2421707361],"iteration":931,"passed_time":0.2547748248,"remaining_time":0.01858872112},
{"learn":[0.2421423894],"iteration":932,"passed_time":0.2548701607,"remaining_time":0.01830257317},
{"learn":[0.2419817825],"iteration":933,"passed_time":0.2550565823,"remaining_time":0.01802327027},
{"learn":[0.2418741796],"iteration":934,"passed_time":0.2554033832,"remaining_time":0.01775531541},
{"learn":[0.241747507],"iteration":935,"passed_time":0.2557373921,"remaining_time":0.01748631741},
{"learn":[0.2416518043],"iteration":936,"passed_time":0.2560459837,"remaining_time":0.01721547169},
{"learn":[0.2414924036],"iteration":937,"passed_time":0.2562994487,"remaining_time":0.01694090173},
{"learn":[0.2414266576],"iteration":938,"passed_time":0.2565303299,"remaining_time":0.01666490961},
{"learn":[0.2414064665],"iteration":939,"passed_time":0.2568027955,"remaining_time":0.0163916678},
{"learn":[0.241332716],"iteration":940,"passed_time":0.2570627607,"remaining_time":0.01611764387},
{"learn":[0.2412580962],"iteration":941,"passed_time":0.2573111007,"remaining_time":0.01584293401},
{"learn":[0.2412558796],"iteration":942,"passed_time":0.2576190672,"remaining_time":0.01557188423},
{"learn":[0.2412518021],"iteration":943,"passed_time":0.2578666155,"remaining_time":0.0152971721},
{"learn":[0.2411354046],"iteration":944,"passed_time":0.2581230806,"remaining_time":0.01502303644},
{"learn":[0.241061065],"iteration":945,"passed_time":0.2583243776,"remaining_time":0.014745789},
{"learn":[0.2408999249],"iteration":946,"passed_time":0.2585215496,"remaining_time":0.01446847109},
{"learn":[0.240804175],"iteration":947,"passed_time":0.2587781397,"remaining_time":0.0141945815},
{"learn":[0.2406956235],"iteration":948,"passed_time":0.2590411051,"remaining_time":0.01392107098},
{"learn":[0.2406678993],"iteration":949,"passed_time":0.2591369409,"remaining_time":0.01363878637},
{"learn":[0.240626946],"iteration":950,"passed_time":0.2593386963,"remaining_time":0.01336235133},
{"learn":[0.2405791018],"iteration":951,"passed_time":0.2595234096,"remaining_time":0.01308521393},
{"learn":[0.240528188],"iteration":952,"passed_time":0.2597903333,"remaining_time":0.01281232494},
{"learn":[0.2404776199],"iteration":953,"passed_time":0.260077716,"remaining_time":0.01254043494},
{"learn":[0.2404179061],"iteration":954,"passed_time":0.2603056804,"remaining_time":0.01226571269},
{"learn":[0.2403118549],"iteration":955,"passed_time":0.2605441867,"remaining_time":0.01199157345},
{"learn":[0.2402579327],"iteration":956,"passed_time":0.2607798597,"remaining_time":0.01171738137},
{"learn":[0.2401866344],"iteration":957,"passed_time":0.261052867,"remaining_time":0.01144490648},
{"learn":[0.2401594558],"iteration":958,"passed_time":0.2612084544,"remaining_time":0.01116741046},
{"learn":[0.2400224741],"iteration":959,"passed_time":0.2615359215,"remaining_time":0.01089733006},
{"learn":[0.2398433814],"iteration":960,"passed_time":0.2618652636,"remaining_time":0.01062720633},
{"learn":[0.2396663784],"iteration":961,"passed_time":0.2621812303,"remaining_time":0.01035643114},
{"learn":[0.2396405566],"iteration":962,"passed_time":0.2623018585,"remaining_time":0.01007805687},
{"learn":[0.2395687431],"iteration":963,"passed_time":0.2625048223,"remaining_time":0.009803084649},
{"learn":[0.2394396462],"iteration":964,"passed_time":0.2628712904,"remaining_time":0.009534191879},
{"learn":[0.2394364253],"iteration":965,"passed_time":0.2631356724,"remaining_time":0.009261503998},
{"learn":[0.239298324],"iteration":966,"passed_time":0.2633245108,"remaining_time":0.00898625528},
{"learn":[0.239295633],"iteration":967,"passed_time":0.2635029322,"remaining_time":0.008710840733},
{"learn":[0.2392702615],"iteration":968,"passed_time":0.263594393,"remaining_time":0.008432844357},
{"learn":[0.2391426922],"iteration":969,"passed_time":0.2637914399,"remaining_time":0.00815849814},
{"learn":[0.239016955],"iteration":970,"passed_time":0.2639738614,"remaining_time":0.007883874336},
{"learn":[0.2388629098],"iteration":971,"passed_time":0.2641510328,"remaining_time":0.00760928901},
{"learn":[0.2387893475],"iteration":972,"passed_time":0.2643760804,"remaining_time":0.007336232448},
{"learn":[0.2386429126],"iteration":973,"passed_time":0.2645926279,"remaining_time":0.007063047561},
{"learn":[0.238556465],"iteration":974,"passed_time":0.2652837713,"remaining_time":0.006802147981},
{"learn":[0.2385510038],"iteration":975,"passed_time":0.2655088189,"remaining_time":0.006528905383},
{"learn":[0.2385481876],"iteration":976,"passed_time":0.2656923238,"remaining_time":0.006254783467},
{"learn":[0.2384493459],"iteration":977,"passed_time":0.2659939152,"remaining_time":0.005983503204},
{"learn":[0.2384384969],"iteration":978,"passed_time":0.2662184212,"remaining_time":0.005710507502},
{"learn":[0.2384053705],"iteration":979,"passed_time":0.2664518857,"remaining_time":0.005437793586},
{"learn":[0.2382953102],"iteration":980,"passed_time":0.2666731416,"remaining_time":0.005164923232},
{"learn":[0.2382158961],"iteration":981,"passed_time":0.2668866889,"remaining_time":0.004892016702},
{"learn":[0.2380944363],"iteration":982,"passed_time":0.2670869026,"remaining_time":0.00461900035},
{"learn":[0.2380868804],"iteration":983,"passed_time":0.2672903247,"remaining_time":0.004346184141},
{"learn":[0.2379434592],"iteration":984,"passed_time":0.2675954995,"remaining_time":0.004075058368},
{"learn":[0.2379410053],"iteration":985,"passed_time":0.2678094635,"remaining_time":0.003802568447},
{"learn":[0.2377723105],"iteration":986,"passed_time":0.2680121772,"remaining_time":0.00353004894},
{"learn":[0.2376272825],"iteration":987,"passed_time":0.2682398916,"remaining_time":0.003257974392},
{"learn":[0.2375036884],"iteration":988,"passed_time":0.2685449414,"remaining_time":0.002986849702},
{"learn":[0.2374260971],"iteration":989,"passed_time":0.2688321991,"remaining_time":0.002715476758},
{"learn":[0.2372871766],"iteration":990,"passed_time":0.2690330378,"remaining_time":0.002443286922},
{"learn":[0.2372301668],"iteration":991,"passed_time":0.2693021283,"remaining_time":0.002171791357},
{"learn":[0.2370634583],"iteration":992,"passed_time":0.2695525933,"remaining_time":0.001900169338},
{"learn":[0.2369234483],"iteration":993,"passed_time":0.2697835577,"remaining_time":0.001628472179},
{"learn":[0.2369027481],"iteration":994,"passed_time":0.2700263975,"remaining_time":0.001356916571},
{"learn":[0.2368556026],"iteration":995,"passed_time":0.2701708597,"remaining_time":0.001085023533},
{"learn":[0.236722242],"iteration":996,"passed_time":0.2705388278,"remaining_time":0.0008140586595},
{"learn":[0.2366777675],"iteration":997,"passed_time":0.2706946237,"remaining_time":0.0005424741957},
{"learn":[0.2366750456],"iteration":998,"passed_time":0.2708743368,"remaining_time":0.0002711454823},
{"learn":[0.2366003947],"iteration":999,"passed_time":0.2711128431,"remaining_time":0}
]}